{
"meta":{"test_sets":[],"test_metrics":[],"learn_metrics":[{"best_value":"Min","name":"RMSE"}],"launch_mode":"Train","parameters":"","iteration_count":1000,"learn_sets":["learn"],"name":"experiment"},
"iterations":[
{"learn":[40.49174416],"iteration":0,"passed_time":0.1639663623,"remaining_time":163.802396},
{"learn":[39.45093279],"iteration":1,"passed_time":0.1803094422,"remaining_time":89.97441167},
{"learn":[38.37933934],"iteration":2,"passed_time":0.2021853975,"remaining_time":67.19294711},
{"learn":[37.34787695],"iteration":3,"passed_time":0.21469794,"remaining_time":53.45978706},
{"learn":[36.35080021],"iteration":4,"passed_time":0.2225848378,"remaining_time":44.29438271},
{"learn":[35.41964815],"iteration":5,"passed_time":0.2334234213,"remaining_time":38.67048012},
{"learn":[34.44680496],"iteration":6,"passed_time":0.2581365781,"remaining_time":36.61851743},
{"learn":[33.58598578],"iteration":7,"passed_time":0.2686648223,"remaining_time":33.31443797},
{"learn":[32.68533499],"iteration":8,"passed_time":0.297869099,"remaining_time":32.79869746},
{"learn":[31.89918633],"iteration":9,"passed_time":0.3211658868,"remaining_time":31.79542279},
{"learn":[31.10490277],"iteration":10,"passed_time":0.3358099631,"remaining_time":30.1923685},
{"learn":[30.33498512],"iteration":11,"passed_time":0.3525901753,"remaining_time":29.02992443},
{"learn":[29.61419655],"iteration":12,"passed_time":0.375361527,"remaining_time":28.49860209},
{"learn":[28.86687971],"iteration":13,"passed_time":0.4114944236,"remaining_time":28.98096441},
{"learn":[28.18128446],"iteration":14,"passed_time":0.4355946204,"remaining_time":28.60404674},
{"learn":[27.44886993],"iteration":15,"passed_time":0.4507374815,"remaining_time":27.72035511},
{"learn":[26.78848697],"iteration":16,"passed_time":0.5045133685,"remaining_time":29.1727436},
{"learn":[26.20202696],"iteration":17,"passed_time":0.5139824273,"remaining_time":28.04059687},
{"learn":[25.65355096],"iteration":18,"passed_time":0.5328425281,"remaining_time":27.51150105},
{"learn":[25.06245738],"iteration":19,"passed_time":0.551318171,"remaining_time":27.01459038},
{"learn":[24.43501418],"iteration":20,"passed_time":0.5933869175,"remaining_time":27.66313296},
{"learn":[23.99772119],"iteration":21,"passed_time":0.6011806626,"remaining_time":26.72521309},
{"learn":[23.47766167],"iteration":22,"passed_time":0.6153416632,"remaining_time":26.13864369},
{"learn":[22.88422175],"iteration":23,"passed_time":0.6249025874,"remaining_time":25.41270522},
{"learn":[22.39815229],"iteration":24,"passed_time":0.6383996482,"remaining_time":24.89758628},
{"learn":[21.91855057],"iteration":25,"passed_time":0.6642569146,"remaining_time":24.88408595},
{"learn":[21.46927238],"iteration":26,"passed_time":0.6726798459,"remaining_time":24.24138852},
{"learn":[20.96260334],"iteration":27,"passed_time":0.6816084694,"remaining_time":23.66155115},
{"learn":[20.53584024],"iteration":28,"passed_time":0.6905596944,"remaining_time":23.12184356},
{"learn":[20.15465242],"iteration":29,"passed_time":0.7095774711,"remaining_time":22.9430049},
{"learn":[19.7312058],"iteration":30,"passed_time":0.7161497041,"remaining_time":22.38545365},
{"learn":[19.3612525],"iteration":31,"passed_time":0.7337789427,"remaining_time":22.19681302},
{"learn":[18.97335409],"iteration":32,"passed_time":0.7507906016,"remaining_time":22.00043975},
{"learn":[18.60251341],"iteration":33,"passed_time":0.7624911082,"remaining_time":21.66371796},
{"learn":[18.2482869],"iteration":34,"passed_time":0.7676552506,"remaining_time":21.16535191},
{"learn":[17.90050975],"iteration":35,"passed_time":0.7717153922,"remaining_time":20.66482328},
{"learn":[17.56525207],"iteration":36,"passed_time":0.7763651454,"remaining_time":20.20647662},
{"learn":[17.24041799],"iteration":37,"passed_time":0.7824038002,"remaining_time":19.80716989},
{"learn":[16.94296733],"iteration":38,"passed_time":0.7865707531,"remaining_time":19.3819101},
{"learn":[16.59468676],"iteration":39,"passed_time":0.7966873961,"remaining_time":19.12049751},
{"learn":[16.31368005],"iteration":40,"passed_time":0.8190868693,"remaining_time":19.15864165},
{"learn":[15.98828808],"iteration":41,"passed_time":0.8274421716,"remaining_time":18.87356191},
{"learn":[15.70470204],"iteration":42,"passed_time":0.8388301209,"remaining_time":18.66884711},
{"learn":[15.41646674],"iteration":43,"passed_time":0.8457415015,"remaining_time":18.37565626},
{"learn":[15.15460286],"iteration":44,"passed_time":0.8527007905,"remaining_time":18.09620566},
{"learn":[14.92929722],"iteration":45,"passed_time":0.8570102472,"remaining_time":17.7736473},
{"learn":[14.678834],"iteration":46,"passed_time":0.8598704043,"remaining_time":17.43524458},
{"learn":[14.48767509],"iteration":47,"passed_time":0.8629999794,"remaining_time":17.11616626},
{"learn":[14.21156073],"iteration":48,"passed_time":0.8680834067,"remaining_time":16.84790448},
{"learn":[13.95482131],"iteration":49,"passed_time":0.8709578503,"remaining_time":16.54819916},
{"learn":[13.74373403],"iteration":50,"passed_time":0.8825889069,"remaining_time":16.42307593},
{"learn":[13.52767254],"iteration":51,"passed_time":0.8966836121,"remaining_time":16.347232},
{"learn":[13.29451659],"iteration":52,"passed_time":0.9513102049,"remaining_time":16.99793894},
{"learn":[13.10603346],"iteration":53,"passed_time":0.9698769215,"remaining_time":16.99080681},
{"learn":[12.8968536],"iteration":54,"passed_time":1.020825363,"remaining_time":17.53963578},
{"learn":[12.73545431],"iteration":55,"passed_time":1.02984504,"remaining_time":17.36024496},
{"learn":[12.5457779],"iteration":56,"passed_time":1.063730456,"remaining_time":17.59820736},
{"learn":[12.35177331],"iteration":57,"passed_time":1.075101992,"remaining_time":17.46113925},
{"learn":[12.15689277],"iteration":58,"passed_time":1.083563954,"remaining_time":17.28192679},
{"learn":[12.01289441],"iteration":59,"passed_time":1.091588792,"remaining_time":17.10155774},
{"learn":[11.82117496],"iteration":60,"passed_time":1.098676887,"remaining_time":16.91241963},
{"learn":[11.65893798],"iteration":61,"passed_time":1.129129397,"remaining_time":17.08263508},
{"learn":[11.50477769],"iteration":62,"passed_time":1.140639758,"remaining_time":16.96475323},
{"learn":[11.36987573],"iteration":63,"passed_time":1.159741055,"remaining_time":16.96121293},
{"learn":[11.22998309],"iteration":64,"passed_time":1.183507344,"remaining_time":17.02429794},
{"learn":[11.11074033],"iteration":65,"passed_time":1.190566815,"remaining_time":16.84832432},
{"learn":[10.96451317],"iteration":66,"passed_time":1.205857732,"remaining_time":16.79201887},
{"learn":[10.83752496],"iteration":67,"passed_time":1.218286205,"remaining_time":16.69768739},
{"learn":[10.71336741],"iteration":68,"passed_time":1.226025458,"remaining_time":16.54245944},
{"learn":[10.58400606],"iteration":69,"passed_time":1.237347305,"remaining_time":16.43904277},
{"learn":[10.47859142],"iteration":70,"passed_time":1.246348613,"remaining_time":16.3078572},
{"learn":[10.34373516],"iteration":71,"passed_time":1.251154333,"remaining_time":16.12598917},
{"learn":[10.2361804],"iteration":72,"passed_time":1.259042222,"remaining_time":15.98811151},
{"learn":[10.13487219],"iteration":73,"passed_time":1.269626298,"remaining_time":15.88748584},
{"learn":[10.00391455],"iteration":74,"passed_time":1.28234275,"remaining_time":15.81556058},
{"learn":[9.889602518],"iteration":75,"passed_time":1.287802972,"remaining_time":15.65697298},
{"learn":[9.785718626],"iteration":76,"passed_time":1.2951464,"remaining_time":15.52493671},
{"learn":[9.673231766],"iteration":77,"passed_time":1.306312195,"remaining_time":15.44128005},
{"learn":[9.560092525],"iteration":78,"passed_time":1.313316621,"remaining_time":15.3109444},
{"learn":[9.455358875],"iteration":79,"passed_time":1.318401063,"remaining_time":15.16161222},
{"learn":[9.337233782],"iteration":80,"passed_time":1.327138015,"remaining_time":15.05728192},
{"learn":[9.237871171],"iteration":81,"passed_time":1.339687192,"remaining_time":14.99796149},
{"learn":[9.142059605],"iteration":82,"passed_time":1.357776842,"remaining_time":15.00098029},
{"learn":[9.057833581],"iteration":83,"passed_time":1.365794234,"remaining_time":14.89366093},
{"learn":[8.985417139],"iteration":84,"passed_time":1.389559027,"remaining_time":14.95819423},
{"learn":[8.915496494],"iteration":85,"passed_time":1.394507993,"remaining_time":14.82070123},
{"learn":[8.820218019],"iteration":86,"passed_time":1.400320267,"remaining_time":14.69531499},
{"learn":[8.7280341],"iteration":87,"passed_time":1.407245601,"remaining_time":14.58418168},
{"learn":[8.658877395],"iteration":88,"passed_time":1.41829401,"remaining_time":14.51759374},
{"learn":[8.5778262],"iteration":89,"passed_time":1.425613765,"remaining_time":14.41453918},
{"learn":[8.511374884],"iteration":90,"passed_time":1.430464216,"remaining_time":14.28892277},
{"learn":[8.455848341],"iteration":91,"passed_time":1.436709622,"remaining_time":14.17969931},
{"learn":[8.393369351],"iteration":92,"passed_time":1.441468688,"remaining_time":14.05819463},
{"learn":[8.342998546],"iteration":93,"passed_time":1.445803928,"remaining_time":13.93508893},
{"learn":[8.284750915],"iteration":94,"passed_time":1.454906597,"remaining_time":13.85989969},
{"learn":[8.240619932],"iteration":95,"passed_time":1.468593721,"remaining_time":13.82925754},
{"learn":[8.187752387],"iteration":96,"passed_time":1.478553832,"remaining_time":13.76426918},
{"learn":[8.107205365],"iteration":97,"passed_time":1.486102426,"remaining_time":13.67820804},
{"learn":[8.045135399],"iteration":98,"passed_time":1.491936918,"remaining_time":13.57813296},
{"learn":[7.992347793],"iteration":99,"passed_time":1.497015029,"remaining_time":13.47313526},
{"learn":[7.935284132],"iteration":100,"passed_time":1.50481891,"remaining_time":13.39437821},
{"learn":[7.877062002],"iteration":101,"passed_time":1.509227966,"remaining_time":13.28712464},
{"learn":[7.819698213],"iteration":102,"passed_time":1.517422483,"remaining_time":13.21483463},
{"learn":[7.776305195],"iteration":103,"passed_time":1.522377516,"remaining_time":13.11586783},
{"learn":[7.737900107],"iteration":104,"passed_time":1.527141001,"remaining_time":13.01705901},
{"learn":[7.685604814],"iteration":105,"passed_time":1.533631211,"remaining_time":12.93458776},
{"learn":[7.636405601],"iteration":106,"passed_time":1.537970448,"remaining_time":12.83558514},
{"learn":[7.584204282],"iteration":107,"passed_time":1.545481979,"remaining_time":12.76453635},
{"learn":[7.539742353],"iteration":108,"passed_time":1.551394976,"remaining_time":12.68158645},
{"learn":[7.492032292],"iteration":109,"passed_time":1.555461297,"remaining_time":12.58509595},
{"learn":[7.442423831],"iteration":110,"passed_time":1.559463326,"remaining_time":12.48975582},
{"learn":[7.407679111],"iteration":111,"passed_time":1.568404846,"remaining_time":12.43520985},
{"learn":[7.363482198],"iteration":112,"passed_time":1.574499539,"remaining_time":12.3591247},
{"learn":[7.319704246],"iteration":113,"passed_time":1.584979514,"remaining_time":12.31834956},
{"learn":[7.276651508],"iteration":114,"passed_time":1.597850118,"remaining_time":12.29649874},
{"learn":[7.221820647],"iteration":115,"passed_time":1.606498322,"remaining_time":12.24262515},
{"learn":[7.192627368],"iteration":116,"passed_time":1.618379399,"remaining_time":12.21392316},
{"learn":[7.151578343],"iteration":117,"passed_time":1.623556351,"remaining_time":12.13539578},
{"learn":[7.089560322],"iteration":118,"passed_time":1.62987047,"remaining_time":12.06652003},
{"learn":[7.058262808],"iteration":119,"passed_time":1.640755425,"remaining_time":12.03220645},
{"learn":[7.030043869],"iteration":120,"passed_time":1.651010482,"remaining_time":11.99370424},
{"learn":[6.969798632],"iteration":121,"passed_time":1.664206848,"remaining_time":11.97683289},
{"learn":[6.934942822],"iteration":122,"passed_time":1.679721157,"remaining_time":11.97654841},
{"learn":[6.895483631],"iteration":123,"passed_time":1.686551903,"remaining_time":11.91467312},
{"learn":[6.842087974],"iteration":124,"passed_time":1.693601998,"remaining_time":11.85521399},
{"learn":[6.801758269],"iteration":125,"passed_time":1.700843508,"remaining_time":11.79791449},
{"learn":[6.747145955],"iteration":126,"passed_time":1.705473045,"remaining_time":11.72344857},
{"learn":[6.715053361],"iteration":127,"passed_time":1.713037565,"remaining_time":11.67006841},
{"learn":[6.66217723],"iteration":128,"passed_time":1.721022062,"remaining_time":11.62023423},
{"learn":[6.632862019],"iteration":129,"passed_time":1.726143695,"remaining_time":11.55188472},
{"learn":[6.595484887],"iteration":130,"passed_time":1.732845547,"remaining_time":11.49498306},
{"learn":[6.556603157],"iteration":131,"passed_time":1.738052958,"remaining_time":11.42901491},
{"learn":[6.522434245],"iteration":132,"passed_time":1.744017971,"remaining_time":11.3688991},
{"learn":[6.486521847],"iteration":133,"passed_time":1.747916674,"remaining_time":11.29623761},
{"learn":[6.454119623],"iteration":134,"passed_time":1.752236038,"remaining_time":11.22729017},
{"learn":[6.432415403],"iteration":135,"passed_time":1.758116947,"remaining_time":11.16921354},
{"learn":[6.413547598],"iteration":136,"passed_time":1.763896012,"remaining_time":11.11125736},
{"learn":[6.390027273],"iteration":137,"passed_time":1.770186339,"remaining_time":11.0572509},
{"learn":[6.365718931],"iteration":138,"passed_time":1.777296739,"remaining_time":11.00901074},
{"learn":[6.340043587],"iteration":139,"passed_time":1.782550538,"remaining_time":10.9499533},
{"learn":[6.316752551],"iteration":140,"passed_time":1.789873395,"remaining_time":10.90426416},
{"learn":[6.28626722],"iteration":141,"passed_time":1.795842282,"remaining_time":10.85093435},
{"learn":[6.246734949],"iteration":142,"passed_time":1.801408319,"remaining_time":10.79585265},
{"learn":[6.215893179],"iteration":143,"passed_time":1.809185898,"remaining_time":10.75460506},
{"learn":[6.19154466],"iteration":144,"passed_time":1.815165488,"remaining_time":10.70321719},
{"learn":[6.161995413],"iteration":145,"passed_time":1.821884429,"remaining_time":10.65677605},
{"learn":[6.132611855],"iteration":146,"passed_time":1.828227608,"remaining_time":10.60869489},
{"learn":[6.109935132],"iteration":147,"passed_time":1.834416734,"remaining_time":10.56029093},
{"learn":[6.081926349],"iteration":148,"passed_time":1.846025484,"remaining_time":10.54340729},
{"learn":[6.064578022],"iteration":149,"passed_time":1.859960638,"remaining_time":10.53977695},
{"learn":[6.033463689],"iteration":150,"passed_time":1.876250084,"remaining_time":10.54924716},
{"learn":[6.01041626],"iteration":151,"passed_time":1.888511163,"remaining_time":10.53590438},
{"learn":[5.997221851],"iteration":152,"passed_time":1.899432201,"remaining_time":10.51515735},
{"learn":[5.977520322],"iteration":153,"passed_time":1.911246477,"remaining_time":10.49944493},
{"learn":[5.95197193],"iteration":154,"passed_time":1.922644098,"remaining_time":10.48151137},
{"learn":[5.918371772],"iteration":155,"passed_time":1.92871164,"remaining_time":10.43482451},
{"learn":[5.895861534],"iteration":156,"passed_time":1.93488804,"remaining_time":10.38923961},
{"learn":[5.874084485],"iteration":157,"passed_time":1.941888991,"remaining_time":10.34854766},
{"learn":[5.847340882],"iteration":158,"passed_time":1.948052768,"remaining_time":10.30385143},
{"learn":[5.830132427],"iteration":159,"passed_time":1.954562172,"remaining_time":10.2614514},
{"learn":[5.803149759],"iteration":160,"passed_time":1.962409456,"remaining_time":10.22646915},
{"learn":[5.771323492],"iteration":161,"passed_time":1.967961339,"remaining_time":10.17994816},
{"learn":[5.725286291],"iteration":162,"passed_time":1.973566739,"remaining_time":10.13420467},
{"learn":[5.695800777],"iteration":163,"passed_time":1.980964532,"remaining_time":10.09808749},
{"learn":[5.671676344],"iteration":164,"passed_time":1.988780033,"remaining_time":10.06443229},
{"learn":[5.642496609],"iteration":165,"passed_time":1.994629549,"remaining_time":10.02121111},
{"learn":[5.604988575],"iteration":166,"passed_time":2.000000059,"remaining_time":9.976048197},
{"learn":[5.573242608],"iteration":167,"passed_time":2.006821397,"remaining_time":9.938544062},
{"learn":[5.542689375],"iteration":168,"passed_time":2.011808617,"remaining_time":9.892384384},
{"learn":[5.509038027],"iteration":169,"passed_time":2.015234711,"remaining_time":9.83908712},
{"learn":[5.487445242],"iteration":170,"passed_time":2.018749833,"remaining_time":9.786804748},
{"learn":[5.46733913],"iteration":171,"passed_time":2.022193748,"remaining_time":9.734746649},
{"learn":[5.437578111],"iteration":172,"passed_time":2.025492406,"remaining_time":9.682556184},
{"learn":[5.399572622],"iteration":173,"passed_time":2.029183866,"remaining_time":9.632792377},
{"learn":[5.382718254],"iteration":174,"passed_time":2.032906006,"remaining_time":9.583699742},
{"learn":[5.352401884],"iteration":175,"passed_time":2.036311881,"remaining_time":9.533641987},
{"learn":[5.325831068],"iteration":176,"passed_time":2.040226239,"remaining_time":9.486475678},
{"learn":[5.298881576],"iteration":177,"passed_time":2.04384672,"remaining_time":9.438438224},
{"learn":[5.281038068],"iteration":178,"passed_time":2.048017833,"remaining_time":9.393422577},
{"learn":[5.248926807],"iteration":179,"passed_time":2.051769849,"remaining_time":9.346951534},
{"learn":[5.223655756],"iteration":180,"passed_time":2.054451755,"remaining_time":9.296110426},
{"learn":[5.20057641],"iteration":181,"passed_time":2.057513226,"remaining_time":9.2475045},
{"learn":[5.17616223],"iteration":182,"passed_time":2.060657789,"remaining_time":9.199767286},
{"learn":[5.163767805],"iteration":183,"passed_time":2.064233671,"remaining_time":9.154427583},
{"learn":[5.145149859],"iteration":184,"passed_time":2.067869268,"remaining_time":9.109802453},
{"learn":[5.130372208],"iteration":185,"passed_time":2.071217707,"remaining_time":9.064361364},
{"learn":[5.100186587],"iteration":186,"passed_time":2.074715509,"remaining_time":9.020019831},
{"learn":[5.07538751],"iteration":187,"passed_time":2.078456796,"remaining_time":8.97716446},
{"learn":[5.053783747],"iteration":188,"passed_time":2.084775679,"remaining_time":8.945783468},
{"learn":[5.020686981],"iteration":189,"passed_time":2.089141898,"remaining_time":8.906341775},
{"learn":[5.001408528],"iteration":190,"passed_time":2.093007553,"remaining_time":8.865147174},
{"learn":[4.985952575],"iteration":191,"passed_time":2.09750849,"remaining_time":8.827014897},
{"learn":[4.961296807],"iteration":192,"passed_time":2.101721604,"remaining_time":8.788027641},
{"learn":[4.942778678],"iteration":193,"passed_time":2.104920809,"remaining_time":8.745186456},
{"learn":[4.910239439],"iteration":194,"passed_time":2.108074253,"remaining_time":8.702562942},
{"learn":[4.903697957],"iteration":195,"passed_time":2.113714947,"remaining_time":8.670544987},
{"learn":[4.882404321],"iteration":196,"passed_time":2.117139008,"remaining_time":8.629759512},
{"learn":[4.876872986],"iteration":197,"passed_time":2.120843938,"remaining_time":8.590489082},
{"learn":[4.859426836],"iteration":198,"passed_time":2.126336529,"remaining_time":8.558771658},
{"learn":[4.84498485],"iteration":199,"passed_time":2.13095614,"remaining_time":8.523824561},
{"learn":[4.83227583],"iteration":200,"passed_time":2.134606817,"remaining_time":8.485327595},
{"learn":[4.806240163],"iteration":201,"passed_time":2.137909632,"remaining_time":8.445801417},
{"learn":[4.793385904],"iteration":202,"passed_time":2.142354923,"remaining_time":8.411117605},
{"learn":[4.77217482],"iteration":203,"passed_time":2.145696022,"remaining_time":8.372421735},
{"learn":[4.748348136],"iteration":204,"passed_time":2.148947005,"remaining_time":8.333721311},
{"learn":[4.733192983],"iteration":205,"passed_time":2.152332629,"remaining_time":8.295884017},
{"learn":[4.714201562],"iteration":206,"passed_time":2.155920119,"remaining_time":8.25915292},
{"learn":[4.700702495],"iteration":207,"passed_time":2.158997887,"remaining_time":8.220799647},
{"learn":[4.686213579],"iteration":208,"passed_time":2.162717702,"remaining_time":8.185213887},
{"learn":[4.670088775],"iteration":209,"passed_time":2.166021218,"remaining_time":8.148365534},
{"learn":[4.651740496],"iteration":210,"passed_time":2.170057725,"remaining_time":8.114576042},
{"learn":[4.635934326],"iteration":211,"passed_time":2.173437397,"remaining_time":8.078625797},
{"learn":[4.616946946],"iteration":212,"passed_time":2.176875856,"remaining_time":8.043198584},
{"learn":[4.601300374],"iteration":213,"passed_time":2.180025277,"remaining_time":8.007008727},
{"learn":[4.594853008],"iteration":214,"passed_time":2.181358046,"remaining_time":7.964493332},
{"learn":[4.587632487],"iteration":215,"passed_time":2.184452805,"remaining_time":7.928754624},
{"learn":[4.573961597],"iteration":216,"passed_time":2.187618549,"remaining_time":7.89357292},
{"learn":[4.569327836],"iteration":217,"passed_time":2.19103279,"remaining_time":7.859576338},
{"learn":[4.553353215],"iteration":218,"passed_time":2.19460026,"remaining_time":7.826405493},
{"learn":[4.532430657],"iteration":219,"passed_time":2.198793312,"remaining_time":7.795721743},
{"learn":[4.512304646],"iteration":220,"passed_time":2.201964471,"remaining_time":7.761675668},
{"learn":[4.499003322],"iteration":221,"passed_time":2.205710141,"remaining_time":7.729921123},
{"learn":[4.494244589],"iteration":222,"passed_time":2.20897351,"remaining_time":7.696737296},
{"learn":[4.489842884],"iteration":223,"passed_time":2.212242743,"remaining_time":7.663840932},
{"learn":[4.477460548],"iteration":224,"passed_time":2.215423406,"remaining_time":7.630902842},
{"learn":[4.46610779],"iteration":225,"passed_time":2.218623184,"remaining_time":7.598293559},
{"learn":[4.450183954],"iteration":226,"passed_time":2.223618443,"remaining_time":7.572057517},
{"learn":[4.431167892],"iteration":227,"passed_time":2.226451752,"remaining_time":7.538687511},
{"learn":[4.41283869],"iteration":228,"passed_time":2.229553466,"remaining_time":7.50648787},
{"learn":[4.400609896],"iteration":229,"passed_time":2.232716368,"remaining_time":7.474746103},
{"learn":[4.385806942],"iteration":230,"passed_time":2.235701236,"remaining_time":7.442659093},
{"learn":[4.366191092],"iteration":231,"passed_time":2.238639416,"remaining_time":7.410668413},
{"learn":[4.358308167],"iteration":232,"passed_time":2.241476066,"remaining_time":7.378592888},
{"learn":[4.351989777],"iteration":233,"passed_time":2.244795212,"remaining_time":7.34834672},
{"learn":[4.341692913],"iteration":234,"passed_time":2.247846529,"remaining_time":7.317457851},
{"learn":[4.328429456],"iteration":235,"passed_time":2.250679424,"remaining_time":7.286097796},
{"learn":[4.311735635],"iteration":236,"passed_time":2.254512613,"remaining_time":7.258198835},
{"learn":[4.306050296],"iteration":237,"passed_time":2.257863787,"remaining_time":7.228958849},
{"learn":[4.292704517],"iteration":238,"passed_time":2.261225882,"remaining_time":7.199970278},
{"learn":[4.274764519],"iteration":239,"passed_time":2.264245138,"remaining_time":7.170109604},
{"learn":[4.262743443],"iteration":240,"passed_time":2.266638139,"remaining_time":7.138499368},
{"learn":[4.250119502],"iteration":241,"passed_time":2.270179699,"remaining_time":7.110728148},
{"learn":[4.244900498],"iteration":242,"passed_time":2.272366058,"remaining_time":7.078934593},
{"learn":[4.220570816],"iteration":243,"passed_time":2.275301561,"remaining_time":7.049704837},
{"learn":[4.197714281],"iteration":244,"passed_time":2.278089036,"remaining_time":7.020233559},
{"learn":[4.178771518],"iteration":245,"passed_time":2.281297117,"remaining_time":6.992268398},
{"learn":[4.165972305],"iteration":246,"passed_time":2.284507345,"remaining_time":6.964510246},
{"learn":[4.161179256],"iteration":247,"passed_time":2.286645666,"remaining_time":6.93369976},
{"learn":[4.156757485],"iteration":248,"passed_time":2.288059095,"remaining_time":6.900933255},
{"learn":[4.138821902],"iteration":249,"passed_time":2.291533373,"remaining_time":6.874600118},
{"learn":[4.125095918],"iteration":250,"passed_time":2.29465925,"remaining_time":6.847409474},
{"learn":[4.119341495],"iteration":251,"passed_time":2.297517594,"remaining_time":6.819615716},
{"learn":[4.102688773],"iteration":252,"passed_time":2.300723487,"remaining_time":6.793045236},
{"learn":[4.092062614],"iteration":253,"passed_time":2.303715712,"remaining_time":6.766031187},
{"learn":[4.080174869],"iteration":254,"passed_time":2.30676411,"remaining_time":6.739369656},
{"learn":[4.065886557],"iteration":255,"passed_time":2.309861246,"remaining_time":6.713034245},
{"learn":[4.061677437],"iteration":256,"passed_time":2.312989525,"remaining_time":6.686969716},
{"learn":[4.057639026],"iteration":257,"passed_time":2.315861466,"remaining_time":6.660345766},
{"learn":[4.043074477],"iteration":258,"passed_time":2.318774106,"remaining_time":6.63402167},
{"learn":[4.030678812],"iteration":259,"passed_time":2.321600713,"remaining_time":6.607632798},
{"learn":[4.018941581],"iteration":260,"passed_time":2.324258392,"remaining_time":6.580946175},
{"learn":[4.001386967],"iteration":261,"passed_time":2.327068233,"remaining_time":6.554871588},
{"learn":[3.988202556],"iteration":262,"passed_time":2.330683278,"remaining_time":6.531230328},
{"learn":[3.976529754],"iteration":263,"passed_time":2.334167765,"remaining_time":6.507376798},
{"learn":[3.971725404],"iteration":264,"passed_time":2.33690615,"remaining_time":6.481607623},
{"learn":[3.958021136],"iteration":265,"passed_time":2.339567779,"remaining_time":6.45579981},
{"learn":[3.941911682],"iteration":266,"passed_time":2.342361444,"remaining_time":6.43052786},
{"learn":[3.919630799],"iteration":267,"passed_time":2.345575385,"remaining_time":6.406571574},
{"learn":[3.898435943],"iteration":268,"passed_time":2.350846117,"remaining_time":6.38835878},
{"learn":[3.884149127],"iteration":269,"passed_time":2.354440175,"remaining_time":6.36570862},
{"learn":[3.869833165],"iteration":270,"passed_time":2.357782129,"remaining_time":6.34252093},
{"learn":[3.857454821],"iteration":271,"passed_time":2.361227033,"remaining_time":6.319754706},
{"learn":[3.841098765],"iteration":272,"passed_time":2.374161815,"remaining_time":6.322401609},
{"learn":[3.827099514],"iteration":273,"passed_time":2.378629619,"remaining_time":6.302500377},
{"learn":[3.812832176],"iteration":274,"passed_time":2.384820753,"remaining_time":6.287254712},
{"learn":[3.800343076],"iteration":275,"passed_time":2.388629712,"remaining_time":6.265825765},
{"learn":[3.783571408],"iteration":276,"passed_time":2.393348865,"remaining_time":6.246899744},
{"learn":[3.774136251],"iteration":277,"passed_time":2.397373393,"remaining_time":6.226271905},
{"learn":[3.763357428],"iteration":278,"passed_time":2.40098832,"remaining_time":6.204704582},
{"learn":[3.743037851],"iteration":279,"passed_time":2.404411823,"remaining_time":6.182773258},
{"learn":[3.733066809],"iteration":280,"passed_time":2.407645075,"remaining_time":6.160486864},
{"learn":[3.71692259],"iteration":281,"passed_time":2.411098768,"remaining_time":6.138896864},
{"learn":[3.70338986],"iteration":282,"passed_time":2.414376532,"remaining_time":6.116989304},
{"learn":[3.696171033],"iteration":283,"passed_time":2.417728258,"remaining_time":6.095399412},
{"learn":[3.680306386],"iteration":284,"passed_time":2.420908404,"remaining_time":6.073507049},
{"learn":[3.670175926],"iteration":285,"passed_time":2.424157075,"remaining_time":6.051916615},
{"learn":[3.65830705],"iteration":286,"passed_time":2.427923696,"remaining_time":6.03174075},
{"learn":[3.643351405],"iteration":287,"passed_time":2.431647585,"remaining_time":6.011573196},
{"learn":[3.630825994],"iteration":288,"passed_time":2.43420594,"remaining_time":5.988651984},
{"learn":[3.620324686],"iteration":289,"passed_time":2.437410024,"remaining_time":5.967452127},
{"learn":[3.609843648],"iteration":290,"passed_time":2.440682125,"remaining_time":5.946541671},
{"learn":[3.59670435],"iteration":291,"passed_time":2.4442635,"remaining_time":5.92650191},
{"learn":[3.590368601],"iteration":292,"passed_time":2.447699591,"remaining_time":5.906223929},
{"learn":[3.568652135],"iteration":293,"passed_time":2.450853526,"remaining_time":5.885382957},
{"learn":[3.558147309],"iteration":294,"passed_time":2.454162316,"remaining_time":5.865031976},
{"learn":[3.545963739],"iteration":295,"passed_time":2.45803093,"remaining_time":5.846127618},
{"learn":[3.533624993],"iteration":296,"passed_time":2.461845573,"remaining_time":5.82719676},
{"learn":[3.519411203],"iteration":297,"passed_time":2.465382924,"remaining_time":5.807714137},
{"learn":[3.507174375],"iteration":298,"passed_time":2.46870087,"remaining_time":5.787823778},
{"learn":[3.498408752],"iteration":299,"passed_time":2.471998326,"remaining_time":5.767996094},
{"learn":[3.489825598],"iteration":300,"passed_time":2.475955229,"remaining_time":5.749809651},
{"learn":[3.478144764],"iteration":301,"passed_time":2.479335698,"remaining_time":5.730385156},
{"learn":[3.465852123],"iteration":302,"passed_time":2.482131439,"remaining_time":5.709721495},
{"learn":[3.456990622],"iteration":303,"passed_time":2.484902095,"remaining_time":5.689117955},
{"learn":[3.443150847],"iteration":304,"passed_time":2.487481699,"remaining_time":5.668196002},
{"learn":[3.433578462],"iteration":305,"passed_time":2.490741446,"remaining_time":5.648936482},
{"learn":[3.420876245],"iteration":306,"passed_time":2.494254982,"remaining_time":5.630354079},
{"learn":[3.410044007],"iteration":307,"passed_time":2.497498256,"remaining_time":5.611262316},
{"learn":[3.391784879],"iteration":308,"passed_time":2.500396817,"remaining_time":5.591502267},
{"learn":[3.381120137],"iteration":309,"passed_time":2.503670767,"remaining_time":5.572686545},
{"learn":[3.369622577],"iteration":310,"passed_time":2.506976426,"remaining_time":5.554041021},
{"learn":[3.357960008],"iteration":311,"passed_time":2.510226696,"remaining_time":5.535371688},
{"learn":[3.341882919],"iteration":312,"passed_time":2.513109869,"remaining_time":5.515995145},
{"learn":[3.33429156],"iteration":313,"passed_time":2.515974175,"remaining_time":5.496682433},
{"learn":[3.318872429],"iteration":314,"passed_time":2.519284101,"remaining_time":5.478443205},
{"learn":[3.307138831],"iteration":315,"passed_time":2.522899237,"remaining_time":5.460959107},
{"learn":[3.298198212],"iteration":316,"passed_time":2.526289242,"remaining_time":5.443077452},
{"learn":[3.287749222],"iteration":317,"passed_time":2.529252413,"remaining_time":5.424371526},
{"learn":[3.275891287],"iteration":318,"passed_time":2.532629659,"remaining_time":5.406648269},
{"learn":[3.261598475],"iteration":319,"passed_time":2.535838075,"remaining_time":5.388655909},
{"learn":[3.258680229],"iteration":320,"passed_time":2.539537611,"remaining_time":5.37179451},
{"learn":[3.247162911],"iteration":321,"passed_time":2.542426344,"remaining_time":5.353307643},
{"learn":[3.235802067],"iteration":322,"passed_time":2.545627575,"remaining_time":5.335572347},
{"learn":[3.225084228],"iteration":323,"passed_time":2.548801989,"remaining_time":5.317870816},
{"learn":[3.21804277],"iteration":324,"passed_time":2.552168764,"remaining_time":5.300658203},
{"learn":[3.20590625],"iteration":325,"passed_time":2.557921864,"remaining_time":5.288464222},
{"learn":[3.202500171],"iteration":326,"passed_time":2.561441373,"remaining_time":5.271712674},
{"learn":[3.195392665],"iteration":327,"passed_time":2.564475356,"remaining_time":5.25404707},
{"learn":[3.188486966],"iteration":328,"passed_time":2.568591132,"remaining_time":5.238676746},
{"learn":[3.18074718],"iteration":329,"passed_time":2.572462518,"remaining_time":5.222878445},
{"learn":[3.171196781],"iteration":330,"passed_time":2.575918109,"remaining_time":5.206311828},
{"learn":[3.165809095],"iteration":331,"passed_time":2.578701679,"remaining_time":5.188472053},
{"learn":[3.158886874],"iteration":332,"passed_time":2.582039917,"remaining_time":5.171833707},
{"learn":[3.145593579],"iteration":333,"passed_time":2.58613238,"remaining_time":5.156778937},
{"learn":[3.136562153],"iteration":334,"passed_time":2.590083791,"remaining_time":5.141509615},
{"learn":[3.128989669],"iteration":335,"passed_time":2.593184051,"remaining_time":5.124625625},
{"learn":[3.119012466],"iteration":336,"passed_time":2.597308882,"remaining_time":5.109839135},
{"learn":[3.109398758],"iteration":337,"passed_time":2.601410249,"remaining_time":5.095069779},
{"learn":[3.102210735],"iteration":338,"passed_time":2.60611783,"remaining_time":5.081545386},
{"learn":[3.090006025],"iteration":339,"passed_time":2.608961679,"remaining_time":5.064455023},
{"learn":[3.08314339],"iteration":340,"passed_time":2.612163362,"remaining_time":5.048139752},
{"learn":[3.075370247],"iteration":341,"passed_time":2.615570806,"remaining_time":5.032297048},
{"learn":[3.067062006],"iteration":342,"passed_time":2.619326379,"remaining_time":5.017193676},
{"learn":[3.060745084],"iteration":343,"passed_time":2.622040968,"remaining_time":5.000171148},
{"learn":[3.046110053],"iteration":344,"passed_time":2.625141762,"remaining_time":4.983964795},
{"learn":[3.039496866],"iteration":345,"passed_time":2.627861376,"remaining_time":4.9671137},
{"learn":[3.032651044],"iteration":346,"passed_time":2.630905086,"remaining_time":4.950953951},
{"learn":[3.027164517],"iteration":347,"passed_time":2.634490867,"remaining_time":4.935885187},
{"learn":[3.016847595],"iteration":348,"passed_time":2.637428607,"remaining_time":4.919673419},
{"learn":[3.009836079],"iteration":349,"passed_time":2.640425655,"remaining_time":4.903647645},
{"learn":[3.003925191],"iteration":350,"passed_time":2.6440925,"remaining_time":4.888934565},
{"learn":[2.997559309],"iteration":351,"passed_time":2.647749977,"remaining_time":4.874267004},
{"learn":[2.982978391],"iteration":352,"passed_time":2.651788737,"remaining_time":4.860360659},
{"learn":[2.96584268],"iteration":353,"passed_time":2.65514838,"remaining_time":4.845270773},
{"learn":[2.960702412],"iteration":354,"passed_time":2.657868934,"remaining_time":4.82908581},
{"learn":[2.954021126],"iteration":355,"passed_time":2.662569491,"remaining_time":4.816558294},
{"learn":[2.942037699],"iteration":356,"passed_time":2.666156655,"remaining_time":4.80206927},
{"learn":[2.929770694],"iteration":357,"passed_time":2.669488239,"remaining_time":4.787182819},
{"learn":[2.914822246],"iteration":358,"passed_time":2.673769072,"remaining_time":4.774055641},
{"learn":[2.908327022],"iteration":359,"passed_time":2.677043184,"remaining_time":4.759187882},
{"learn":[2.89759159],"iteration":360,"passed_time":2.682145135,"remaining_time":4.747619781},
{"learn":[2.888900114],"iteration":361,"passed_time":2.685501719,"remaining_time":4.733011317},
{"learn":[2.88245156],"iteration":362,"passed_time":2.688748497,"remaining_time":4.718272156},
{"learn":[2.874748835],"iteration":363,"passed_time":2.691497279,"remaining_time":4.702726016},
{"learn":[2.863382212],"iteration":364,"passed_time":2.69550802,"remaining_time":4.68944546},
{"learn":[2.854053341],"iteration":365,"passed_time":2.699161549,"remaining_time":4.675596781},
{"learn":[2.84753473],"iteration":366,"passed_time":2.716394004,"remaining_time":4.685224535},
{"learn":[2.838606914],"iteration":367,"passed_time":2.719409929,"remaining_time":4.670290965},
{"learn":[2.834792879],"iteration":368,"passed_time":2.722384757,"remaining_time":4.655351712},
{"learn":[2.828523766],"iteration":369,"passed_time":2.725277911,"remaining_time":4.640338065},
{"learn":[2.821185728],"iteration":370,"passed_time":2.72844265,"remaining_time":4.625850206},
{"learn":[2.807554616],"iteration":371,"passed_time":2.731554207,"remaining_time":4.611333446},
{"learn":[2.801074214],"iteration":372,"passed_time":2.734430829,"remaining_time":4.596482922},
{"learn":[2.794455502],"iteration":373,"passed_time":2.737355032,"remaining_time":4.58177607},
{"learn":[2.791293911],"iteration":374,"passed_time":2.740493902,"remaining_time":4.567489836},
{"learn":[2.784646302],"iteration":375,"passed_time":2.74409951,"remaining_time":4.554037484},
{"learn":[2.779539811],"iteration":376,"passed_time":2.747855296,"remaining_time":4.540885542},
{"learn":[2.774557032],"iteration":377,"passed_time":2.750235844,"remaining_time":4.525520357},
{"learn":[2.764353822],"iteration":378,"passed_time":2.753498232,"remaining_time":4.511668607},
{"learn":[2.755334298],"iteration":379,"passed_time":2.756168909,"remaining_time":4.496907167},
{"learn":[2.742258322],"iteration":380,"passed_time":2.760180877,"remaining_time":4.484388355},
{"learn":[2.72868014],"iteration":381,"passed_time":2.763745021,"remaining_time":4.47118959},
{"learn":[2.721888821],"iteration":382,"passed_time":2.767067229,"remaining_time":4.457651385},
{"learn":[2.712317781],"iteration":383,"passed_time":2.76994769,"remaining_time":4.443457753},
{"learn":[2.708702947],"iteration":384,"passed_time":2.773686738,"remaining_time":4.4306944},
{"learn":[2.700248877],"iteration":385,"passed_time":2.77692687,"remaining_time":4.417184192},
{"learn":[2.688100105],"iteration":386,"passed_time":2.779696265,"remaining_time":4.402981422},
{"learn":[2.679913746],"iteration":387,"passed_time":2.782295298,"remaining_time":4.388568873},
{"learn":[2.671617426],"iteration":388,"passed_time":2.784721778,"remaining_time":4.373946031},
{"learn":[2.664145964],"iteration":389,"passed_time":2.787135222,"remaining_time":4.359365348},
{"learn":[2.656558451],"iteration":390,"passed_time":2.790768277,"remaining_time":4.346746497},
{"learn":[2.6458169],"iteration":391,"passed_time":2.794028683,"remaining_time":4.333595508},
{"learn":[2.63795477],"iteration":392,"passed_time":2.797000597,"remaining_time":4.320049269},
{"learn":[2.632327464],"iteration":393,"passed_time":2.79949016,"remaining_time":4.305814815},
{"learn":[2.625300666],"iteration":394,"passed_time":2.802198976,"remaining_time":4.291975646},
{"learn":[2.619521609],"iteration":395,"passed_time":2.804862999,"remaining_time":4.278124373},
{"learn":[2.610036939],"iteration":396,"passed_time":2.80798796,"remaining_time":4.265029571},
{"learn":[2.604839779],"iteration":397,"passed_time":2.811245649,"remaining_time":4.252185629},
{"learn":[2.598902165],"iteration":398,"passed_time":2.81369331,"remaining_time":4.238169622},
{"learn":[2.59229522],"iteration":399,"passed_time":2.816418061,"remaining_time":4.224627092},
{"learn":[2.588647959],"iteration":400,"passed_time":2.818688015,"remaining_time":4.210459154},
{"learn":[2.58067166],"iteration":401,"passed_time":2.822094968,"remaining_time":4.198041769},
{"learn":[2.571596532],"iteration":402,"passed_time":2.825384999,"remaining_time":4.185495892},
{"learn":[2.566968659],"iteration":403,"passed_time":2.827860987,"remaining_time":4.171794921},
{"learn":[2.561598726],"iteration":404,"passed_time":2.830613568,"remaining_time":4.158555736},
{"learn":[2.555682777],"iteration":405,"passed_time":2.833069875,"remaining_time":4.144934743},
{"learn":[2.547391303],"iteration":406,"passed_time":2.83567302,"remaining_time":4.131582558},
{"learn":[2.543082404],"iteration":407,"passed_time":2.838901273,"remaining_time":4.119190083},
{"learn":[2.537264857],"iteration":408,"passed_time":2.841964903,"remaining_time":4.106604542},
{"learn":[2.52669708],"iteration":409,"passed_time":2.844728023,"remaining_time":4.093633008},
{"learn":[2.516960952],"iteration":410,"passed_time":2.847103022,"remaining_time":4.08015494},
{"learn":[2.509981932],"iteration":411,"passed_time":2.849884586,"remaining_time":4.06731101},
{"learn":[2.499199638],"iteration":412,"passed_time":2.853475562,"remaining_time":4.055666235},
{"learn":[2.491727607],"iteration":413,"passed_time":2.857019638,"remaining_time":4.04399398},
{"learn":[2.484321625],"iteration":414,"passed_time":2.859712922,"remaining_time":4.031161589},
{"learn":[2.479965965],"iteration":415,"passed_time":2.862487659,"remaining_time":4.018492291},
{"learn":[2.472435783],"iteration":416,"passed_time":2.865390792,"remaining_time":4.006049956},
{"learn":[2.46902583],"iteration":417,"passed_time":2.86838848,"remaining_time":3.993784917},
{"learn":[2.463253747],"iteration":418,"passed_time":2.871936886,"remaining_time":3.982327758},
{"learn":[2.453972355],"iteration":419,"passed_time":2.874780903,"remaining_time":3.969935533},
{"learn":[2.448519455],"iteration":420,"passed_time":2.87754141,"remaining_time":3.957473816},
{"learn":[2.443625138],"iteration":421,"passed_time":2.880656431,"remaining_time":3.945543643},
{"learn":[2.438121621],"iteration":422,"passed_time":2.883698714,"remaining_time":3.933555929},
{"learn":[2.430958125],"iteration":423,"passed_time":2.887150942,"remaining_time":3.922167318},
{"learn":[2.424239851],"iteration":424,"passed_time":2.889694006,"remaining_time":3.909586008},
{"learn":[2.414603535],"iteration":425,"passed_time":2.892549527,"remaining_time":3.897472837},
{"learn":[2.409324805],"iteration":426,"passed_time":2.895181108,"remaining_time":3.885102517},
{"learn":[2.404882681],"iteration":427,"passed_time":2.897792423,"remaining_time":3.872750621},
{"learn":[2.400637523],"iteration":428,"passed_time":2.901133989,"remaining_time":3.861416102},
{"learn":[2.396307323],"iteration":429,"passed_time":2.904117973,"remaining_time":3.849644755},
{"learn":[2.391582115],"iteration":430,"passed_time":2.907598219,"remaining_time":3.838569342},
{"learn":[2.386974375],"iteration":431,"passed_time":2.910356336,"remaining_time":3.826579628},
{"learn":[2.376578187],"iteration":432,"passed_time":2.91269132,"remaining_time":3.814078472},
{"learn":[2.375333735],"iteration":433,"passed_time":2.916351554,"remaining_time":3.803352487},
{"learn":[2.368776101],"iteration":434,"passed_time":2.919163617,"remaining_time":3.791557341},
{"learn":[2.361878369],"iteration":435,"passed_time":2.921770102,"remaining_time":3.779537472},
{"learn":[2.358198377],"iteration":436,"passed_time":2.924148685,"remaining_time":3.76726707},
{"learn":[2.351340045],"iteration":437,"passed_time":2.926647171,"remaining_time":3.755195685},
{"learn":[2.346355902],"iteration":438,"passed_time":2.929376954,"remaining_time":3.743463488},
{"learn":[2.340782262],"iteration":439,"passed_time":2.932809834,"remaining_time":3.732667062},
{"learn":[2.335576075],"iteration":440,"passed_time":2.936111644,"remaining_time":3.721737889},
{"learn":[2.327613603],"iteration":441,"passed_time":2.938537494,"remaining_time":3.709737379},
{"learn":[2.319255541],"iteration":442,"passed_time":2.940914705,"remaining_time":3.697718941},
{"learn":[2.309827069],"iteration":443,"passed_time":2.943638174,"remaining_time":3.686177534},
{"learn":[2.302950273],"iteration":444,"passed_time":2.94676683,"remaining_time":3.675181103},
{"learn":[2.299106931],"iteration":445,"passed_time":2.95086235,"remaining_time":3.665420946},
{"learn":[2.293909205],"iteration":446,"passed_time":2.953552213,"remaining_time":3.653947146},
{"learn":[2.285865251],"iteration":447,"passed_time":2.956304386,"remaining_time":3.642589333},
{"learn":[2.281132171],"iteration":448,"passed_time":2.959363983,"remaining_time":3.631647115},
{"learn":[2.278043412],"iteration":449,"passed_time":2.962536597,"remaining_time":3.620878063},
{"learn":[2.272572083],"iteration":450,"passed_time":2.965723328,"remaining_time":3.610159882},
{"learn":[2.267707247],"iteration":451,"passed_time":2.968383353,"remaining_time":3.598836454},
{"learn":[2.262699646],"iteration":452,"passed_time":2.971149553,"remaining_time":3.587679483},
{"learn":[2.255577512],"iteration":453,"passed_time":2.973544393,"remaining_time":3.576112861},
{"learn":[2.250685468],"iteration":454,"passed_time":2.976579489,"remaining_time":3.565353454},
{"learn":[2.242222019],"iteration":455,"passed_time":2.979654674,"remaining_time":3.554675752},
{"learn":[2.241124428],"iteration":456,"passed_time":2.982318702,"remaining_time":3.543542791},
{"learn":[2.233698809],"iteration":457,"passed_time":2.985371964,"remaining_time":3.532907434},
{"learn":[2.22909746],"iteration":458,"passed_time":2.988097061,"remaining_time":3.521918322},
{"learn":[2.225242069],"iteration":459,"passed_time":2.990971089,"remaining_time":3.511139974},
{"learn":[2.216889062],"iteration":460,"passed_time":2.994167736,"remaining_time":3.500773123},
{"learn":[2.21232948],"iteration":461,"passed_time":2.997024621,"remaining_time":3.490041658},
{"learn":[2.20687125],"iteration":462,"passed_time":2.999518483,"remaining_time":3.478923165},
{"learn":[2.203285361],"iteration":463,"passed_time":3.001729226,"remaining_time":3.467514796},
{"learn":[2.200792865],"iteration":464,"passed_time":3.004067634,"remaining_time":3.45629287},
{"learn":[2.198535952],"iteration":465,"passed_time":3.008329703,"remaining_time":3.447313436},
{"learn":[2.19413755],"iteration":466,"passed_time":3.011778306,"remaining_time":3.437425776},
{"learn":[2.189685829],"iteration":467,"passed_time":3.014120775,"remaining_time":3.426308231},
{"learn":[2.186011338],"iteration":468,"passed_time":3.016510324,"remaining_time":3.415281412},
{"learn":[2.18215721],"iteration":469,"passed_time":3.019267318,"remaining_time":3.404705698},
{"learn":[2.178996892],"iteration":470,"passed_time":3.022027411,"remaining_time":3.394166668},
{"learn":[2.170916072],"iteration":471,"passed_time":3.025552445,"remaining_time":3.384516295},
{"learn":[2.167486782],"iteration":472,"passed_time":3.028783397,"remaining_time":3.374564165},
{"learn":[2.164087183],"iteration":473,"passed_time":3.031335982,"remaining_time":3.363887608},
{"learn":[2.155855234],"iteration":474,"passed_time":3.034182335,"remaining_time":3.353569949},
{"learn":[2.148025204],"iteration":475,"passed_time":3.036867849,"remaining_time":3.343106624},
{"learn":[2.1445031],"iteration":476,"passed_time":3.04078186,"remaining_time":3.334022878},
{"learn":[2.137986371],"iteration":477,"passed_time":3.044311985,"remaining_time":3.324541541},
{"learn":[2.131084906],"iteration":478,"passed_time":3.047691236,"remaining_time":3.314920948},
{"learn":[2.124348193],"iteration":479,"passed_time":3.051024481,"remaining_time":3.305276521},
{"learn":[2.121973939],"iteration":480,"passed_time":3.054208259,"remaining_time":3.295497061},
{"learn":[2.117526466],"iteration":481,"passed_time":3.058002103,"remaining_time":3.286400601},
{"learn":[2.112742857],"iteration":482,"passed_time":3.061454074,"remaining_time":3.276960158},
{"learn":[2.109058099],"iteration":483,"passed_time":3.064444344,"remaining_time":3.267052235},
{"learn":[2.105483096],"iteration":484,"passed_time":3.067730829,"remaining_time":3.257487376},
{"learn":[2.099010102],"iteration":485,"passed_time":3.070974385,"remaining_time":3.247902951},
{"learn":[2.095202342],"iteration":486,"passed_time":3.073913522,"remaining_time":3.238023895},
{"learn":[2.089774593],"iteration":487,"passed_time":3.076773638,"remaining_time":3.228090375},
{"learn":[2.082366057],"iteration":488,"passed_time":3.079219053,"remaining_time":3.217752426},
{"learn":[2.078124005],"iteration":489,"passed_time":3.082232347,"remaining_time":3.208037749},
{"learn":[2.0750549],"iteration":490,"passed_time":3.086049208,"remaining_time":3.199183395},
{"learn":[2.072916087],"iteration":491,"passed_time":3.089482163,"remaining_time":3.189953128},
{"learn":[2.068833125],"iteration":492,"passed_time":3.092430716,"remaining_time":3.180248222},
{"learn":[2.062729484],"iteration":493,"passed_time":3.095001156,"remaining_time":3.17018337},
{"learn":[2.054554829],"iteration":494,"passed_time":3.097807075,"remaining_time":3.160389037},
{"learn":[2.051443936],"iteration":495,"passed_time":3.100197891,"remaining_time":3.150201083},
{"learn":[2.047890256],"iteration":496,"passed_time":3.103520512,"remaining_time":3.14098756},
{"learn":[2.045095601],"iteration":497,"passed_time":3.106722746,"remaining_time":3.131676343},
{"learn":[2.04078351],"iteration":498,"passed_time":3.109038806,"remaining_time":3.121499883},
{"learn":[2.038555294],"iteration":499,"passed_time":3.111864857,"remaining_time":3.111864857},
{"learn":[2.035804749],"iteration":500,"passed_time":3.114310734,"remaining_time":3.101878356},
{"learn":[2.032165473],"iteration":501,"passed_time":3.117282866,"remaining_time":3.092443959},
{"learn":[2.029324245],"iteration":502,"passed_time":3.120212558,"remaining_time":3.082993323},
{"learn":[2.025108886],"iteration":503,"passed_time":3.122755485,"remaining_time":3.073187938},
{"learn":[2.019753702],"iteration":504,"passed_time":3.125653417,"remaining_time":3.06375929},
{"learn":[2.013342382],"iteration":505,"passed_time":3.128123932,"remaining_time":3.053939175},
{"learn":[2.010214476],"iteration":506,"passed_time":3.130561286,"remaining_time":3.044115806},
{"learn":[2.0068368],"iteration":507,"passed_time":3.13384948,"remaining_time":3.03514556},
{"learn":[2.001282442],"iteration":508,"passed_time":3.136957528,"remaining_time":3.026023863},
{"learn":[1.999755679],"iteration":509,"passed_time":3.139795771,"remaining_time":3.016666525},
{"learn":[1.996256363],"iteration":510,"passed_time":3.142352811,"remaining_time":3.007065606},
{"learn":[1.992613341],"iteration":511,"passed_time":3.145247214,"remaining_time":2.99781375},
{"learn":[1.98711743],"iteration":512,"passed_time":3.149236773,"remaining_time":2.989626332},
{"learn":[1.982783678],"iteration":513,"passed_time":3.152510016,"remaining_time":2.980777953},
{"learn":[1.979912309],"iteration":514,"passed_time":3.155171914,"remaining_time":2.971375492},
{"learn":[1.976087975],"iteration":515,"passed_time":3.157753031,"remaining_time":2.961923385},
{"learn":[1.970744167],"iteration":516,"passed_time":3.160674831,"remaining_time":2.952816138},
{"learn":[1.967780189],"iteration":517,"passed_time":3.163265807,"remaining_time":2.94342494},
{"learn":[1.962782567],"iteration":518,"passed_time":3.166381197,"remaining_time":2.934545965},
{"learn":[1.962182981],"iteration":519,"passed_time":3.16881749,"remaining_time":2.925062299},
{"learn":[1.955363091],"iteration":520,"passed_time":3.171079504,"remaining_time":2.915445456},
{"learn":[1.953777042],"iteration":521,"passed_time":3.173346759,"remaining_time":2.905861592},
{"learn":[1.95186611],"iteration":522,"passed_time":3.175697155,"remaining_time":2.896381535},
{"learn":[1.946102512],"iteration":523,"passed_time":3.178357772,"remaining_time":2.887210495},
{"learn":[1.939358497],"iteration":524,"passed_time":3.181998884,"remaining_time":2.878951371},
{"learn":[1.936424228],"iteration":525,"passed_time":3.18475941,"remaining_time":2.869916275},
{"learn":[1.933463959],"iteration":526,"passed_time":3.187063957,"remaining_time":2.860495734},
{"learn":[1.930171221],"iteration":527,"passed_time":3.189833691,"remaining_time":2.851517996},
{"learn":[1.923696201],"iteration":528,"passed_time":3.192188349,"remaining_time":2.842194164},
{"learn":[1.919586261],"iteration":529,"passed_time":3.19459199,"remaining_time":2.832940066},
{"learn":[1.914233382],"iteration":530,"passed_time":3.197749013,"remaining_time":2.824377188},
{"learn":[1.911463315],"iteration":531,"passed_time":3.200089041,"remaining_time":2.815115924},
{"learn":[1.907602734],"iteration":532,"passed_time":3.202387291,"remaining_time":2.805844024},
{"learn":[1.90258543],"iteration":533,"passed_time":3.204674434,"remaining_time":2.796588551},
{"learn":[1.899983567],"iteration":534,"passed_time":3.207042575,"remaining_time":2.787429528},
{"learn":[1.894500803],"iteration":535,"passed_time":3.209547182,"remaining_time":2.778413979},
{"learn":[1.888879328],"iteration":536,"passed_time":3.212479428,"remaining_time":2.769791388},
{"learn":[1.884238148],"iteration":537,"passed_time":3.215048851,"remaining_time":2.760878381},
{"learn":[1.881760591],"iteration":538,"passed_time":3.217382432,"remaining_time":2.751787201},
{"learn":[1.877708193],"iteration":539,"passed_time":3.219787423,"remaining_time":2.742781879},
{"learn":[1.871642803],"iteration":540,"passed_time":3.222217413,"remaining_time":2.733822167},
{"learn":[1.867697384],"iteration":541,"passed_time":3.224591312,"remaining_time":2.724839153},
{"learn":[1.864482864],"iteration":542,"passed_time":3.227732406,"remaining_time":2.716526169},
{"learn":[1.861175591],"iteration":543,"passed_time":3.231003188,"remaining_time":2.708340908},
{"learn":[1.856871714],"iteration":544,"passed_time":3.233698978,"remaining_time":2.699693642},
{"learn":[1.852677543],"iteration":545,"passed_time":3.236327379,"remaining_time":2.691012143},
{"learn":[1.848130473],"iteration":546,"passed_time":3.239222494,"remaining_time":2.682573656},
{"learn":[1.845445969],"iteration":547,"passed_time":3.241958169,"remaining_time":2.674023891},
{"learn":[1.841807535],"iteration":548,"passed_time":3.245836668,"remaining_time":2.66643413},
{"learn":[1.83938255],"iteration":549,"passed_time":3.248495826,"remaining_time":2.657860221},
{"learn":[1.837142789],"iteration":550,"passed_time":3.251188196,"remaining_time":2.649334846},
{"learn":[1.833762681],"iteration":551,"passed_time":3.253909573,"remaining_time":2.640854146},
{"learn":[1.828286658],"iteration":552,"passed_time":3.256968797,"remaining_time":2.632667364},
{"learn":[1.824976383],"iteration":553,"passed_time":3.260803807,"remaining_time":2.625123642},
{"learn":[1.821209134],"iteration":554,"passed_time":3.263562365,"remaining_time":2.616730185},
{"learn":[1.817965284],"iteration":555,"passed_time":3.265990591,"remaining_time":2.608093206},
{"learn":[1.813357929],"iteration":556,"passed_time":3.268536984,"remaining_time":2.599572503},
{"learn":[1.807077592],"iteration":557,"passed_time":3.271053048,"remaining_time":2.591049189},
{"learn":[1.805705011],"iteration":558,"passed_time":3.273807128,"remaining_time":2.582735141},
{"learn":[1.803804036],"iteration":559,"passed_time":3.27733276,"remaining_time":2.575047169},
{"learn":[1.798497324],"iteration":560,"passed_time":3.280058448,"remaining_time":2.566748054},
{"learn":[1.791747568],"iteration":561,"passed_time":3.282736912,"remaining_time":2.55843197},
{"learn":[1.786814016],"iteration":562,"passed_time":3.285325776,"remaining_time":2.550066366},
{"learn":[1.785500382],"iteration":563,"passed_time":3.287846253,"remaining_time":2.54166838},
{"learn":[1.782331487],"iteration":564,"passed_time":3.290885655,"remaining_time":2.533690726},
{"learn":[1.777535756],"iteration":565,"passed_time":3.293674017,"remaining_time":2.525538027},
{"learn":[1.775211013],"iteration":566,"passed_time":3.29594628,"remaining_time":2.517010122},
{"learn":[1.771847029],"iteration":567,"passed_time":3.298259542,"remaining_time":2.508535427},
{"learn":[1.770789077],"iteration":568,"passed_time":3.300595235,"remaining_time":2.500099378},
{"learn":[1.767708811],"iteration":569,"passed_time":3.30304146,"remaining_time":2.491768119},
{"learn":[1.765161529],"iteration":570,"passed_time":3.305622294,"remaining_time":2.483558606},
{"learn":[1.763246144],"iteration":571,"passed_time":3.308390226,"remaining_time":2.47550877},
{"learn":[1.76025433],"iteration":572,"passed_time":3.311181592,"remaining_time":2.467494834},
{"learn":[1.757264365],"iteration":573,"passed_time":3.313562323,"remaining_time":2.459194337},
{"learn":[1.753111501],"iteration":574,"passed_time":3.317217546,"remaining_time":2.451856447},
{"learn":[1.749052184],"iteration":575,"passed_time":3.319556328,"remaining_time":2.443562297},
{"learn":[1.746015242],"iteration":576,"passed_time":3.322592799,"remaining_time":2.435800267},
{"learn":[1.741582729],"iteration":577,"passed_time":3.325592986,"remaining_time":2.428028097},
{"learn":[1.735791372],"iteration":578,"passed_time":3.328387186,"remaining_time":2.420122634},
{"learn":[1.731381302],"iteration":579,"passed_time":3.33152179,"remaining_time":2.412481296},
{"learn":[1.728525867],"iteration":580,"passed_time":3.334864398,"remaining_time":2.405005478},
{"learn":[1.728386562],"iteration":581,"passed_time":3.337008319,"remaining_time":2.39668295},
{"learn":[1.726457022],"iteration":582,"passed_time":3.340730073,"remaining_time":2.38951019},
{"learn":[1.723122827],"iteration":583,"passed_time":3.34376996,"remaining_time":2.381863533},
{"learn":[1.721717932],"iteration":584,"passed_time":3.347211127,"remaining_time":2.374517295},
{"learn":[1.718364216],"iteration":585,"passed_time":3.349963835,"remaining_time":2.366697999},
{"learn":[1.714461548],"iteration":586,"passed_time":3.352956392,"remaining_time":2.359064719},
{"learn":[1.712779326],"iteration":587,"passed_time":3.356210016,"remaining_time":2.351630147},
{"learn":[1.709299007],"iteration":588,"passed_time":3.359481396,"remaining_time":2.344222162},
{"learn":[1.704843945],"iteration":589,"passed_time":3.362004758,"remaining_time":2.336308391},
{"learn":[1.701315683],"iteration":590,"passed_time":3.364433459,"remaining_time":2.328347351},
{"learn":[1.697188558],"iteration":591,"passed_time":3.36689619,"remaining_time":2.320428455},
{"learn":[1.696454978],"iteration":592,"passed_time":3.369912425,"remaining_time":2.312907853},
{"learn":[1.69495092],"iteration":593,"passed_time":3.373097036,"remaining_time":2.305517503},
{"learn":[1.691136498],"iteration":594,"passed_time":3.375810531,"remaining_time":2.297820614},
{"learn":[1.687389878],"iteration":595,"passed_time":3.378235541,"remaining_time":2.289944897},
{"learn":[1.684423375],"iteration":596,"passed_time":3.380470666,"remaining_time":2.28195926},
{"learn":[1.683187074],"iteration":597,"passed_time":3.382883911,"remaining_time":2.274112596},
{"learn":[1.68007243],"iteration":598,"passed_time":3.386057221,"remaining_time":2.266792898},
{"learn":[1.679379659],"iteration":599,"passed_time":3.388710151,"remaining_time":2.2591401},
{"learn":[1.677414266],"iteration":600,"passed_time":3.391054836,"remaining_time":2.251299301},
{"learn":[1.674408335],"iteration":601,"passed_time":3.393454427,"remaining_time":2.243513059},
{"learn":[1.673518461],"iteration":602,"passed_time":3.395797361,"remaining_time":2.235707383},
{"learn":[1.672155267],"iteration":603,"passed_time":3.398153035,"remaining_time":2.227928149},
{"learn":[1.669248854],"iteration":604,"passed_time":3.401068456,"remaining_time":2.220532298},
{"learn":[1.664147359],"iteration":605,"passed_time":3.403629182,"remaining_time":2.212920623},
{"learn":[1.659782092],"iteration":606,"passed_time":3.405888105,"remaining_time":2.20513019},
{"learn":[1.657521096],"iteration":607,"passed_time":3.408193589,"remaining_time":2.197387972},
{"learn":[1.654189991],"iteration":608,"passed_time":3.410518713,"remaining_time":2.189676218},
{"learn":[1.651790556],"iteration":609,"passed_time":3.412852812,"remaining_time":2.181987863},
{"learn":[1.649244372],"iteration":610,"passed_time":3.415467037,"remaining_time":2.174495381},
{"learn":[1.646983702],"iteration":611,"passed_time":3.418081062,"remaining_time":2.167018713},
{"learn":[1.643513139],"iteration":612,"passed_time":3.420512432,"remaining_time":2.159442596},
{"learn":[1.640047004],"iteration":613,"passed_time":3.422853364,"remaining_time":2.151826382},
{"learn":[1.63747902],"iteration":614,"passed_time":3.425317208,"remaining_time":2.144304269},
{"learn":[1.635222299],"iteration":615,"passed_time":3.42764162,"remaining_time":2.136711659},
{"learn":[1.632570857],"iteration":616,"passed_time":3.429954791,"remaining_time":2.129129149},
{"learn":[1.629844809],"iteration":617,"passed_time":3.43311465,"remaining_time":2.122087049},
{"learn":[1.628344057],"iteration":618,"passed_time":3.435946977,"remaining_time":2.114855894},
{"learn":[1.627146777],"iteration":619,"passed_time":3.438295538,"remaining_time":2.107342427},
{"learn":[1.624596037],"iteration":620,"passed_time":3.4406556,"remaining_time":2.099852613},
{"learn":[1.622264714],"iteration":621,"passed_time":3.443015138,"remaining_time":2.092378974},
{"learn":[1.618796123],"iteration":622,"passed_time":3.445398187,"remaining_time":2.084935982},
{"learn":[1.616161412],"iteration":623,"passed_time":3.448273959,"remaining_time":2.077806103},
{"learn":[1.612866789],"iteration":624,"passed_time":3.450943849,"remaining_time":2.070566309},
{"learn":[1.609557257],"iteration":625,"passed_time":3.453319491,"remaining_time":2.063165319},
{"learn":[1.607239782],"iteration":626,"passed_time":3.455747691,"remaining_time":2.055811625},
{"learn":[1.60406163],"iteration":627,"passed_time":3.458088529,"remaining_time":2.048421867},
{"learn":[1.602270874],"iteration":628,"passed_time":3.46037097,"remaining_time":2.04101372},
{"learn":[1.599934535],"iteration":629,"passed_time":3.462947587,"remaining_time":2.033794614},
{"learn":[1.597788971],"iteration":630,"passed_time":3.465560947,"remaining_time":2.02661171},
{"learn":[1.596428134],"iteration":631,"passed_time":3.46793768,"remaining_time":2.019305485},
{"learn":[1.594065767],"iteration":632,"passed_time":3.470230491,"remaining_time":2.011966177},
{"learn":[1.591888326],"iteration":633,"passed_time":3.472479145,"remaining_time":2.004617298},
{"learn":[1.589292223],"iteration":634,"passed_time":3.474717503,"remaining_time":1.997278565},
{"learn":[1.587058584],"iteration":635,"passed_time":3.477009737,"remaining_time":1.989986705},
{"learn":[1.584239755],"iteration":636,"passed_time":3.479930423,"remaining_time":1.983068671},
{"learn":[1.580579948],"iteration":637,"passed_time":3.482698522,"remaining_time":1.976076591},
{"learn":[1.578737944],"iteration":638,"passed_time":3.485056769,"remaining_time":1.968866187},
{"learn":[1.575853057],"iteration":639,"passed_time":3.487362639,"remaining_time":1.961641484},
{"learn":[1.573812423],"iteration":640,"passed_time":3.489752228,"remaining_time":1.954479017},
{"learn":[1.57091114],"iteration":641,"passed_time":3.492092323,"remaining_time":1.947303819},
{"learn":[1.568284228],"iteration":642,"passed_time":3.494999976,"remaining_time":1.940458774},
{"learn":[1.566319998],"iteration":643,"passed_time":3.497651726,"remaining_time":1.933484495},
{"learn":[1.563573488],"iteration":644,"passed_time":3.500042694,"remaining_time":1.926380088},
{"learn":[1.558538846],"iteration":645,"passed_time":3.502427505,"remaining_time":1.919286899},
{"learn":[1.556750102],"iteration":646,"passed_time":3.504802413,"remaining_time":1.912202862},
{"learn":[1.553082194],"iteration":647,"passed_time":3.507612748,"remaining_time":1.905369888},
{"learn":[1.549836624],"iteration":648,"passed_time":3.510274419,"remaining_time":1.898468908},
{"learn":[1.548132941],"iteration":649,"passed_time":3.512538397,"remaining_time":1.891366829},
{"learn":[1.544713008],"iteration":650,"passed_time":3.514871528,"remaining_time":1.884316687},
{"learn":[1.54283858],"iteration":651,"passed_time":3.517319794,"remaining_time":1.877342467},
{"learn":[1.540341908],"iteration":652,"passed_time":3.520033245,"remaining_time":1.870523026},
{"learn":[1.539042163],"iteration":653,"passed_time":3.523141192,"remaining_time":1.863924851},
{"learn":[1.537435123],"iteration":654,"passed_time":3.526685327,"remaining_time":1.857567081},
{"learn":[1.533759279],"iteration":655,"passed_time":3.529034538,"remaining_time":1.850591282},
{"learn":[1.531309346],"iteration":656,"passed_time":3.531566969,"remaining_time":1.843725221},
{"learn":[1.529266844],"iteration":657,"passed_time":3.534036511,"remaining_time":1.836839646},
{"learn":[1.527514532],"iteration":658,"passed_time":3.536547337,"remaining_time":1.829988835},
{"learn":[1.52462925],"iteration":659,"passed_time":3.539919413,"remaining_time":1.823594849},
{"learn":[1.522337807],"iteration":660,"passed_time":3.542425585,"remaining_time":1.81676592},
{"learn":[1.519666057],"iteration":661,"passed_time":3.544923522,"remaining_time":1.809945846},
{"learn":[1.517437534],"iteration":662,"passed_time":3.54742371,"remaining_time":1.803139955},
{"learn":[1.515598073],"iteration":663,"passed_time":3.550030024,"remaining_time":1.796400735},
{"learn":[1.511171488],"iteration":664,"passed_time":3.55312242,"remaining_time":1.789918813},
{"learn":[1.509136476],"iteration":665,"passed_time":3.556578467,"remaining_time":1.783629441},
{"learn":[1.507279607],"iteration":666,"passed_time":3.559723585,"remaining_time":1.777193334},
{"learn":[1.505632815],"iteration":667,"passed_time":3.562481817,"remaining_time":1.770574795},
{"learn":[1.502013468],"iteration":668,"passed_time":3.565332259,"remaining_time":1.76401342},
{"learn":[1.499728681],"iteration":669,"passed_time":3.568485911,"remaining_time":1.757612464},
{"learn":[1.498857915],"iteration":670,"passed_time":3.57191304,"remaining_time":1.751355276},
{"learn":[1.49577601],"iteration":671,"passed_time":3.575058444,"remaining_time":1.744969003},
{"learn":[1.493981717],"iteration":672,"passed_time":3.577911934,"remaining_time":1.738450523},
{"learn":[1.491001167],"iteration":673,"passed_time":3.58113488,"remaining_time":1.732121619},
{"learn":[1.48801875],"iteration":674,"passed_time":3.584626763,"remaining_time":1.725931404},
{"learn":[1.48418078],"iteration":675,"passed_time":3.587988707,"remaining_time":1.719686895},
{"learn":[1.480484989],"iteration":676,"passed_time":3.590831435,"remaining_time":1.713203181},
{"learn":[1.478929936],"iteration":677,"passed_time":3.593645931,"remaining_time":1.706716799},
{"learn":[1.476906334],"iteration":678,"passed_time":3.596942217,"remaining_time":1.700469001},
{"learn":[1.475228138],"iteration":679,"passed_time":3.599942354,"remaining_time":1.69409052},
{"learn":[1.472766245],"iteration":680,"passed_time":3.603984911,"remaining_time":1.688210259},
{"learn":[1.470861653],"iteration":681,"passed_time":3.60719743,"remaining_time":1.681948362},
{"learn":[1.469345287],"iteration":682,"passed_time":3.610303311,"remaining_time":1.6756459},
{"learn":[1.467737693],"iteration":683,"passed_time":3.613205679,"remaining_time":1.669258764},
{"learn":[1.465464869],"iteration":684,"passed_time":3.617645964,"remaining_time":1.66358902},
{"learn":[1.463897911],"iteration":685,"passed_time":3.621074939,"remaining_time":1.657459957},
{"learn":[1.462089756],"iteration":686,"passed_time":3.624071533,"remaining_time":1.651141761},
{"learn":[1.459916524],"iteration":687,"passed_time":3.627574442,"remaining_time":1.645062828},
{"learn":[1.458323791],"iteration":688,"passed_time":3.630951193,"remaining_time":1.638934428},
{"learn":[1.456325794],"iteration":689,"passed_time":3.634582955,"remaining_time":1.632928574},
{"learn":[1.454555995],"iteration":690,"passed_time":3.637946258,"remaining_time":1.626809542},
{"learn":[1.452308189],"iteration":691,"passed_time":3.640620921,"remaining_time":1.620391971},
{"learn":[1.44949927],"iteration":692,"passed_time":3.642933549,"remaining_time":1.613824819},
{"learn":[1.447538818],"iteration":693,"passed_time":3.645688427,"remaining_time":1.607464926},
{"learn":[1.446086583],"iteration":694,"passed_time":3.648496723,"remaining_time":1.60113885},
{"learn":[1.443346111],"iteration":695,"passed_time":3.651557163,"remaining_time":1.594933014},
{"learn":[1.442049948],"iteration":696,"passed_time":3.654024423,"remaining_time":1.588478336},
{"learn":[1.440582838],"iteration":697,"passed_time":3.656384783,"remaining_time":1.581988832},
{"learn":[1.437664311],"iteration":698,"passed_time":3.658981314,"remaining_time":1.575612841},
{"learn":[1.43468178],"iteration":699,"passed_time":3.661362142,"remaining_time":1.569155204},
{"learn":[1.432679058],"iteration":700,"passed_time":3.664345239,"remaining_time":1.562966086},
{"learn":[1.430221998],"iteration":701,"passed_time":3.667295459,"remaining_time":1.556772147},
{"learn":[1.427134022],"iteration":702,"passed_time":3.669705539,"remaining_time":1.550359239},
{"learn":[1.425627452],"iteration":703,"passed_time":3.67206562,"remaining_time":1.543936681},
{"learn":[1.423573669],"iteration":704,"passed_time":3.674688644,"remaining_time":1.537635674},
{"learn":[1.42082919],"iteration":705,"passed_time":3.677041893,"remaining_time":1.531232743},
{"learn":[1.419498734],"iteration":706,"passed_time":3.680321146,"remaining_time":1.525225029},
{"learn":[1.417736261],"iteration":707,"passed_time":3.68306208,"remaining_time":1.519003005},
{"learn":[1.415679215],"iteration":708,"passed_time":3.685482982,"remaining_time":1.512659447},
{"learn":[1.413102736],"iteration":709,"passed_time":3.688288682,"remaining_time":1.50648411},
{"learn":[1.411761729],"iteration":710,"passed_time":3.690494155,"remaining_time":1.500074277},
{"learn":[1.409547735],"iteration":711,"passed_time":3.692663954,"remaining_time":1.493661824},
{"learn":[1.407810095],"iteration":712,"passed_time":3.69574171,"remaining_time":1.487626747},
{"learn":[1.405970991],"iteration":713,"passed_time":3.698540864,"remaining_time":1.481488357},
{"learn":[1.404364601],"iteration":714,"passed_time":3.701169944,"remaining_time":1.475291516},
{"learn":[1.402590574],"iteration":715,"passed_time":3.70366765,"remaining_time":1.469052532},
{"learn":[1.399922966],"iteration":716,"passed_time":3.705998402,"remaining_time":1.462758086},
{"learn":[1.398327738],"iteration":717,"passed_time":3.708830186,"remaining_time":1.456671466},
{"learn":[1.397428008],"iteration":718,"passed_time":3.71202753,"remaining_time":1.450736767},
{"learn":[1.395702429],"iteration":719,"passed_time":3.715215158,"remaining_time":1.444805895},
{"learn":[1.393202319],"iteration":720,"passed_time":3.717598195,"remaining_time":1.438571285},
{"learn":[1.391487343],"iteration":721,"passed_time":3.720033043,"remaining_time":1.432367294},
{"learn":[1.390034838],"iteration":722,"passed_time":3.722551329,"remaining_time":1.426205696},
{"learn":[1.387509988],"iteration":723,"passed_time":3.725080847,"remaining_time":1.420058444},
{"learn":[1.384645643],"iteration":724,"passed_time":3.728686115,"remaining_time":1.414329216},
{"learn":[1.383920588],"iteration":725,"passed_time":3.731163009,"remaining_time":1.408179979},
{"learn":[1.382940995],"iteration":726,"passed_time":3.733396718,"remaining_time":1.401949524},
{"learn":[1.381343166],"iteration":727,"passed_time":3.735952924,"remaining_time":1.395850543},
{"learn":[1.380401163],"iteration":728,"passed_time":3.73858647,"remaining_time":1.389790032},
{"learn":[1.37811431],"iteration":729,"passed_time":3.741207927,"remaining_time":1.383734439},
{"learn":[1.375813532],"iteration":730,"passed_time":3.744712362,"remaining_time":1.378013167},
{"learn":[1.374380297],"iteration":731,"passed_time":3.747397837,"remaining_time":1.371998115},
{"learn":[1.37286596],"iteration":732,"passed_time":3.749722299,"remaining_time":1.365860646},
{"learn":[1.371558553],"iteration":733,"passed_time":3.752360267,"remaining_time":1.359847181},
{"learn":[1.370144223],"iteration":734,"passed_time":3.754728339,"remaining_time":1.353745591},
{"learn":[1.368250666],"iteration":735,"passed_time":3.75756789,"remaining_time":1.347823265},
{"learn":[1.365110299],"iteration":736,"passed_time":3.760968964,"remaining_time":1.342109685},
{"learn":[1.363499524],"iteration":737,"passed_time":3.76345776,"remaining_time":1.3360785},
{"learn":[1.363275912],"iteration":738,"passed_time":3.766162202,"remaining_time":1.330133065},
{"learn":[1.36086692],"iteration":739,"passed_time":3.768455036,"remaining_time":1.324051769},
{"learn":[1.357923863],"iteration":740,"passed_time":3.770708878,"remaining_time":1.317967071},
{"learn":[1.357808392],"iteration":741,"passed_time":3.77325876,"remaining_time":1.311995633},
{"learn":[1.355948305],"iteration":742,"passed_time":3.776536281,"remaining_time":1.306285093},
{"learn":[1.353145327],"iteration":743,"passed_time":3.779181627,"remaining_time":1.30036357},
{"learn":[1.351698756],"iteration":744,"passed_time":3.781543061,"remaining_time":1.294353665},
{"learn":[1.349765488],"iteration":745,"passed_time":3.783805075,"remaining_time":1.28831969},
{"learn":[1.348015752],"iteration":746,"passed_time":3.786577607,"remaining_time":1.282468721},
{"learn":[1.345665915],"iteration":747,"passed_time":3.789620147,"remaining_time":1.276716948},
{"learn":[1.344960692],"iteration":748,"passed_time":3.792460126,"remaining_time":1.270904528},
{"learn":[1.343090672],"iteration":749,"passed_time":3.795036922,"remaining_time":1.265012307},
{"learn":[1.340821134],"iteration":750,"passed_time":3.797291551,"remaining_time":1.259022099},
{"learn":[1.338160848],"iteration":751,"passed_time":3.799662769,"remaining_time":1.253080275},
{"learn":[1.335897768],"iteration":752,"passed_time":3.802188149,"remaining_time":1.247198503},
{"learn":[1.333384189],"iteration":753,"passed_time":3.80474439,"remaining_time":1.241335703},
{"learn":[1.33234896],"iteration":754,"passed_time":3.807795441,"remaining_time":1.235642229},
{"learn":[1.33130784],"iteration":755,"passed_time":3.810740761,"remaining_time":1.229921621},
{"learn":[1.329267418],"iteration":756,"passed_time":3.813019245,"remaining_time":1.223994289},
{"learn":[1.327723958],"iteration":757,"passed_time":3.815782598,"remaining_time":1.218231384},
{"learn":[1.325771171],"iteration":758,"passed_time":3.818356637,"remaining_time":1.212416271},
{"learn":[1.324877891],"iteration":759,"passed_time":3.821273724,"remaining_time":1.206718018},
{"learn":[1.323508907],"iteration":760,"passed_time":3.824253516,"remaining_time":1.201046768},
{"learn":[1.321487741],"iteration":761,"passed_time":3.826656807,"remaining_time":1.19520252},
{"learn":[1.319157084],"iteration":762,"passed_time":3.829289187,"remaining_time":1.18943845},
{"learn":[1.315996015],"iteration":763,"passed_time":3.83164592,"remaining_time":1.183597431},
{"learn":[1.314349151],"iteration":764,"passed_time":3.834057684,"remaining_time":1.177782426},
{"learn":[1.31277575],"iteration":765,"passed_time":3.837378853,"remaining_time":1.172254114},
{"learn":[1.311047145],"iteration":766,"passed_time":3.840236735,"remaining_time":1.16659082},
{"learn":[1.310876658],"iteration":767,"passed_time":3.842680168,"remaining_time":1.160809634},
{"learn":[1.308788769],"iteration":768,"passed_time":3.845055626,"remaining_time":1.15501671},
{"learn":[1.306489579],"iteration":769,"passed_time":3.847324731,"remaining_time":1.149200894},
{"learn":[1.305096878],"iteration":770,"passed_time":3.849866307,"remaining_time":1.143475207},
{"learn":[1.303705677],"iteration":771,"passed_time":3.853177655,"remaining_time":1.137985111},
{"learn":[1.302194067],"iteration":772,"passed_time":3.855684567,"remaining_time":1.13226442},
{"learn":[1.301211346],"iteration":773,"passed_time":3.858361272,"remaining_time":1.126601612},
{"learn":[1.299538109],"iteration":774,"passed_time":3.860653601,"remaining_time":1.120834917},
{"learn":[1.296627894],"iteration":775,"passed_time":3.863265539,"remaining_time":1.115169434},
{"learn":[1.295007834],"iteration":776,"passed_time":3.866114915,"remaining_time":1.109579956},
{"learn":[1.294085565],"iteration":777,"passed_time":3.869316785,"remaining_time":1.104098106},
{"learn":[1.293951276],"iteration":778,"passed_time":3.872352193,"remaining_time":1.098574884},
{"learn":[1.292947406],"iteration":779,"passed_time":3.874649054,"remaining_time":1.092849733},
{"learn":[1.291583224],"iteration":780,"passed_time":3.876972044,"remaining_time":1.087140688},
{"learn":[1.290719205],"iteration":781,"passed_time":3.879242047,"remaining_time":1.081425532},
{"learn":[1.289835674],"iteration":782,"passed_time":3.881743555,"remaining_time":1.075783335},
{"learn":[1.28804473],"iteration":783,"passed_time":3.884816962,"remaining_time":1.070306714},
{"learn":[1.286710128],"iteration":784,"passed_time":3.888043585,"remaining_time":1.064878179},
{"learn":[1.285059203],"iteration":785,"passed_time":3.891074929,"remaining_time":1.05940208},
{"learn":[1.284149894],"iteration":786,"passed_time":3.893696282,"remaining_time":1.05382123},
{"learn":[1.282157548],"iteration":787,"passed_time":3.896017309,"remaining_time":1.048167093},
{"learn":[1.280203799],"iteration":788,"passed_time":3.898537098,"remaining_time":1.04257456},
{"learn":[1.278381908],"iteration":789,"passed_time":3.902052922,"remaining_time":1.037254574},
{"learn":[1.277616869],"iteration":790,"passed_time":3.905230259,"remaining_time":1.031849714},
{"learn":[1.276334713],"iteration":791,"passed_time":3.908295264,"remaining_time":1.026420978},
{"learn":[1.274574829],"iteration":792,"passed_time":3.911443153,"remaining_time":1.021019839},
{"learn":[1.273599044],"iteration":793,"passed_time":3.914883046,"remaining_time":1.015700135},
{"learn":[1.271560381],"iteration":794,"passed_time":3.918247997,"remaining_time":1.010365836},
{"learn":[1.268250966],"iteration":795,"passed_time":3.921345366,"remaining_time":1.004967908},
{"learn":[1.26728299],"iteration":796,"passed_time":3.923650181,"remaining_time":0.9993738856},
{"learn":[1.265438027],"iteration":797,"passed_time":3.926144952,"remaining_time":0.993836191},
{"learn":[1.262342899],"iteration":798,"passed_time":3.928838467,"remaining_time":0.9883561099},
{"learn":[1.261493096],"iteration":799,"passed_time":3.932048019,"remaining_time":0.9830120048},
{"learn":[1.258386179],"iteration":800,"passed_time":3.934947623,"remaining_time":0.9775962258},
{"learn":[1.257045127],"iteration":801,"passed_time":3.937234043,"remaining_time":0.9720353372},
{"learn":[1.254676074],"iteration":802,"passed_time":3.93948528,"remaining_time":0.9664739729},
{"learn":[1.251852136],"iteration":803,"passed_time":3.94174778,"remaining_time":0.9609235881},
{"learn":[1.250215457],"iteration":804,"passed_time":3.944076686,"remaining_time":0.9553974582},
{"learn":[1.248630426],"iteration":805,"passed_time":3.946828513,"remaining_time":0.9499810566},
{"learn":[1.246235794],"iteration":806,"passed_time":3.950034382,"remaining_time":0.9446798461},
{"learn":[1.245109093],"iteration":807,"passed_time":3.952285123,"remaining_time":0.9391568608},
{"learn":[1.243294435],"iteration":808,"passed_time":3.954819592,"remaining_time":0.933708952},
{"learn":[1.241743675],"iteration":809,"passed_time":3.957555171,"remaining_time":0.9283154104},
{"learn":[1.240182804],"iteration":810,"passed_time":3.959906108,"remaining_time":0.9228387847},
{"learn":[1.238954989],"iteration":811,"passed_time":3.96312747,"remaining_time":0.9175713847},
{"learn":[1.23731984],"iteration":812,"passed_time":3.965648612,"remaining_time":0.9121479588},
{"learn":[1.235390965],"iteration":813,"passed_time":3.968026607,"remaining_time":0.9066989544},
{"learn":[1.233872559],"iteration":814,"passed_time":3.97092849,"remaining_time":0.9013764058},
{"learn":[1.232024862],"iteration":815,"passed_time":3.973280809,"remaining_time":0.8959358688},
{"learn":[1.229728824],"iteration":816,"passed_time":3.975683951,"remaining_time":0.8905142755},
{"learn":[1.227049073],"iteration":817,"passed_time":3.979076395,"remaining_time":0.8853201758},
{"learn":[1.225509531],"iteration":818,"passed_time":3.981984513,"remaining_time":0.8800234394},
{"learn":[1.223549661],"iteration":819,"passed_time":3.984738881,"remaining_time":0.8746987787},
{"learn":[1.22020733],"iteration":820,"passed_time":3.987203775,"remaining_time":0.8693172665},
{"learn":[1.218250255],"iteration":821,"passed_time":3.989707482,"remaining_time":0.8639512553},
{"learn":[1.215742842],"iteration":822,"passed_time":3.992365203,"remaining_time":0.8586253231},
{"learn":[1.213884493],"iteration":823,"passed_time":3.995587263,"remaining_time":0.8534264056},
{"learn":[1.213028142],"iteration":824,"passed_time":3.997834743,"remaining_time":0.8480255516},
{"learn":[1.211489654],"iteration":825,"passed_time":4.000254818,"remaining_time":0.8426686906},
{"learn":[1.210594423],"iteration":826,"passed_time":4.002577186,"remaining_time":0.8372984923},
{"learn":[1.208137397],"iteration":827,"passed_time":4.004794624,"remaining_time":0.8319138591},
{"learn":[1.205982474],"iteration":828,"passed_time":4.007035303,"remaining_time":0.8265416608},
{"learn":[1.203980511],"iteration":829,"passed_time":4.009953853,"remaining_time":0.8213158494},
{"learn":[1.202366402],"iteration":830,"passed_time":4.012911906,"remaining_time":0.8161036247},
{"learn":[1.200771605],"iteration":831,"passed_time":4.015486788,"remaining_time":0.8108194477},
{"learn":[1.199978327],"iteration":832,"passed_time":4.017892578,"remaining_time":0.8055078757},
{"learn":[1.198791717],"iteration":833,"passed_time":4.02016357,"remaining_time":0.800176442},
{"learn":[1.197672341],"iteration":834,"passed_time":4.022564416,"remaining_time":0.7948779985},
{"learn":[1.196071577],"iteration":835,"passed_time":4.025690644,"remaining_time":0.7897287867},
{"learn":[1.193811214],"iteration":836,"passed_time":4.028621973,"remaining_time":0.7845464536},
{"learn":[1.192878579],"iteration":837,"passed_time":4.030886933,"remaining_time":0.7792406721},
{"learn":[1.191582785],"iteration":838,"passed_time":4.033171726,"remaining_time":0.773945945},
{"learn":[1.190437399],"iteration":839,"passed_time":4.035387255,"remaining_time":0.7686451914},
{"learn":[1.187742718],"iteration":840,"passed_time":4.037682101,"remaining_time":0.7633667705},
{"learn":[1.186007037],"iteration":841,"passed_time":4.040479194,"remaining_time":0.7581896825},
{"learn":[1.184047369],"iteration":842,"passed_time":4.043467164,"remaining_time":0.7530537897},
{"learn":[1.181057736],"iteration":843,"passed_time":4.045841059,"remaining_time":0.7478094848},
{"learn":[1.179918748],"iteration":844,"passed_time":4.048199128,"remaining_time":0.7425690708},
{"learn":[1.178000454],"iteration":845,"passed_time":4.050530962,"remaining_time":0.7373306952},
{"learn":[1.174833922],"iteration":846,"passed_time":4.052801574,"remaining_time":0.7320881238},
{"learn":[1.172914648],"iteration":847,"passed_time":4.055263448,"remaining_time":0.7268868445},
{"learn":[1.171962846],"iteration":848,"passed_time":4.057983214,"remaining_time":0.7217378862},
{"learn":[1.169336814],"iteration":849,"passed_time":4.060462841,"remaining_time":0.716552266},
{"learn":[1.166717545],"iteration":850,"passed_time":4.062804944,"remaining_time":0.7113489268},
{"learn":[1.165979617],"iteration":851,"passed_time":4.065084982,"remaining_time":0.7061415227},
{"learn":[1.164197178],"iteration":852,"passed_time":4.067396857,"remaining_time":0.700946469},
{"learn":[1.16315373],"iteration":853,"passed_time":4.069633187,"remaining_time":0.6957452522},
{"learn":[1.161928535],"iteration":854,"passed_time":4.072211616,"remaining_time":0.6906089874},
{"learn":[1.160556097],"iteration":855,"passed_time":4.074950702,"remaining_time":0.6855057255},
{"learn":[1.158934102],"iteration":856,"passed_time":4.077202824,"remaining_time":0.6803267256},
{"learn":[1.157675074],"iteration":857,"passed_time":4.07945674,"remaining_time":0.6751548451},
{"learn":[1.155284391],"iteration":858,"passed_time":4.081839001,"remaining_time":0.6700108256},
{"learn":[1.15377335],"iteration":859,"passed_time":4.084193681,"remaining_time":0.6648687387},
{"learn":[1.151807691],"iteration":860,"passed_time":4.086444419,"remaining_time":0.6597163463},
{"learn":[1.150761749],"iteration":861,"passed_time":4.089350439,"remaining_time":0.6546755924},
{"learn":[1.148421299],"iteration":862,"passed_time":4.091925174,"remaining_time":0.6495871945},
{"learn":[1.145650251],"iteration":863,"passed_time":4.094214291,"remaining_time":0.6444596569},
{"learn":[1.143990689],"iteration":864,"passed_time":4.096426656,"remaining_time":0.6393267035},
{"learn":[1.142286377],"iteration":865,"passed_time":4.098605692,"remaining_time":0.634195338},
{"learn":[1.14113809],"iteration":866,"passed_time":4.100895721,"remaining_time":0.6290878096},
{"learn":[1.139410056],"iteration":867,"passed_time":4.103277936,"remaining_time":0.6240007921},
{"learn":[1.137003542],"iteration":868,"passed_time":4.106276143,"remaining_time":0.6190128593},
{"learn":[1.13598762],"iteration":869,"passed_time":4.10859869,"remaining_time":0.6139285399},
{"learn":[1.135213682],"iteration":870,"passed_time":4.111008062,"remaining_time":0.6088634213},
{"learn":[1.133037041],"iteration":871,"passed_time":4.113374353,"remaining_time":0.6037980702},
{"learn":[1.13131053],"iteration":872,"passed_time":4.115709085,"remaining_time":0.5987343113},
{"learn":[1.129650898],"iteration":873,"passed_time":4.117993922,"remaining_time":0.5936696043},
{"learn":[1.129231679],"iteration":874,"passed_time":4.120921623,"remaining_time":0.588703089},
{"learn":[1.127711341],"iteration":875,"passed_time":4.12366451,"remaining_time":0.5837150676},
{"learn":[1.12566582],"iteration":876,"passed_time":4.126337066,"remaining_time":0.5787223023},
{"learn":[1.124405618],"iteration":877,"passed_time":4.128578932,"remaining_time":0.5736749768},
{"learn":[1.123392674],"iteration":878,"passed_time":4.130914361,"remaining_time":0.5686469143},
{"learn":[1.121919551],"iteration":879,"passed_time":4.133730024,"remaining_time":0.5636904579},
{"learn":[1.120425381],"iteration":880,"passed_time":4.136780119,"remaining_time":0.5587705269},
{"learn":[1.117693806],"iteration":881,"passed_time":4.139476035,"remaining_time":0.5538074513},
{"learn":[1.117039695],"iteration":882,"passed_time":4.141754948,"remaining_time":0.548794257},
{"learn":[1.115155215],"iteration":883,"passed_time":4.144104666,"remaining_time":0.5437965399},
{"learn":[1.114468879],"iteration":884,"passed_time":4.146419609,"remaining_time":0.5388002881},
{"learn":[1.111715366],"iteration":885,"passed_time":4.14897548,"remaining_time":0.5338410888},
{"learn":[1.110015571],"iteration":886,"passed_time":4.151768757,"remaining_time":0.528917553},
{"learn":[1.109142883],"iteration":887,"passed_time":4.154568231,"remaining_time":0.5239995967},
{"learn":[1.107752795],"iteration":888,"passed_time":4.156824254,"remaining_time":0.5190185514},
{"learn":[1.106422289],"iteration":889,"passed_time":4.159192142,"remaining_time":0.5140574557},
{"learn":[1.105591254],"iteration":890,"passed_time":4.161527678,"remaining_time":0.5090982232},
{"learn":[1.103119975],"iteration":891,"passed_time":4.164375058,"remaining_time":0.5042068456},
{"learn":[1.102399711],"iteration":892,"passed_time":4.167186167,"remaining_time":0.4993156997},
{"learn":[1.101202924],"iteration":893,"passed_time":4.170649906,"remaining_time":0.4945065884},
{"learn":[1.100364772],"iteration":894,"passed_time":4.173873,"remaining_time":0.4896722514},
{"learn":[1.098826982],"iteration":895,"passed_time":4.17661606,"remaining_time":0.4847857927},
{"learn":[1.097271143],"iteration":896,"passed_time":4.179429004,"remaining_time":0.4799121376},
{"learn":[1.095641665],"iteration":897,"passed_time":4.181786172,"remaining_time":0.4749913024},
{"learn":[1.09337969],"iteration":898,"passed_time":4.185218985,"remaining_time":0.4701970161},
{"learn":[1.092347883],"iteration":899,"passed_time":4.188275199,"remaining_time":0.465363911},
{"learn":[1.090587052],"iteration":900,"passed_time":4.191255593,"remaining_time":0.4605264192},
{"learn":[1.088894147],"iteration":901,"passed_time":4.193931809,"remaining_time":0.4556599969},
{"learn":[1.086881906],"iteration":902,"passed_time":4.196633987,"remaining_time":0.4508012145},
{"learn":[1.085255422],"iteration":903,"passed_time":4.199663196,"remaining_time":0.4459819323},
{"learn":[1.08445564],"iteration":904,"passed_time":4.202757161,"remaining_time":0.4411734036},
{"learn":[1.083666793],"iteration":905,"passed_time":4.205448659,"remaining_time":0.4363269028},
{"learn":[1.081524753],"iteration":906,"passed_time":4.208295057,"remaining_time":0.4315010367},
{"learn":[1.080024963],"iteration":907,"passed_time":4.210595372,"remaining_time":0.4266242007},
{"learn":[1.079438095],"iteration":908,"passed_time":4.21285553,"remaining_time":0.4217490134},
{"learn":[1.078262201],"iteration":909,"passed_time":4.216017612,"remaining_time":0.4169687748},
{"learn":[1.076650113],"iteration":910,"passed_time":4.21896484,"remaining_time":0.4121710986},
{"learn":[1.074337433],"iteration":911,"passed_time":4.221774025,"remaining_time":0.4073641603},
{"learn":[1.073465372],"iteration":912,"passed_time":4.224500231,"remaining_time":0.4025536912},
{"learn":[1.072355437],"iteration":913,"passed_time":4.227314794,"remaining_time":0.3977560966},
{"learn":[1.07093257],"iteration":914,"passed_time":4.230117827,"remaining_time":0.3929617653},
{"learn":[1.069605797],"iteration":915,"passed_time":4.232915985,"remaining_time":0.3881713349},
{"learn":[1.067948384],"iteration":916,"passed_time":4.235408957,"remaining_time":0.3833576264},
{"learn":[1.066607095],"iteration":917,"passed_time":4.238841717,"remaining_time":0.3786329203},
{"learn":[1.065421146],"iteration":918,"passed_time":4.241314347,"remaining_time":0.3738264005},
{"learn":[1.063011176],"iteration":919,"passed_time":4.243796377,"remaining_time":0.3690257719},
{"learn":[1.061427306],"iteration":920,"passed_time":4.246742966,"remaining_time":0.3642700264},
{"learn":[1.059909784],"iteration":921,"passed_time":4.249481719,"remaining_time":0.3595006226},
{"learn":[1.057952149],"iteration":922,"passed_time":4.252239027,"remaining_time":0.3547371669},
{"learn":[1.055495521],"iteration":923,"passed_time":4.255030051,"remaining_time":0.3499808267},
{"learn":[1.054635618],"iteration":924,"passed_time":4.257909602,"remaining_time":0.3452359137},
{"learn":[1.053976898],"iteration":925,"passed_time":4.260596804,"remaining_time":0.3404796582},
{"learn":[1.053014561],"iteration":926,"passed_time":4.263714257,"remaining_time":0.3357617484},
{"learn":[1.051403275],"iteration":927,"passed_time":4.266749211,"remaining_time":0.3310408871},
{"learn":[1.049668248],"iteration":928,"passed_time":4.269634773,"remaining_time":0.3263122378},
{"learn":[1.047374103],"iteration":929,"passed_time":4.272603748,"remaining_time":0.3215938305},
{"learn":[1.046873767],"iteration":930,"passed_time":4.275400269,"remaining_time":0.3168664002},
{"learn":[1.045634616],"iteration":931,"passed_time":4.278474082,"remaining_time":0.3121633451},
{"learn":[1.044834728],"iteration":932,"passed_time":4.281381784,"remaining_time":0.3074518537},
{"learn":[1.043424743],"iteration":933,"passed_time":4.284631459,"remaining_time":0.30276839},
{"learn":[1.041130304],"iteration":934,"passed_time":4.286996373,"remaining_time":0.2980264858},
{"learn":[1.04014029],"iteration":935,"passed_time":4.289327341,"remaining_time":0.2932873396},
{"learn":[1.037952182],"iteration":936,"passed_time":4.291737134,"remaining_time":0.2885586334},
{"learn":[1.036575545],"iteration":937,"passed_time":4.295249369,"remaining_time":0.2839077408},
{"learn":[1.035373289],"iteration":938,"passed_time":4.298732968,"remaining_time":0.2792574133},
{"learn":[1.033928423],"iteration":939,"passed_time":4.301717683,"remaining_time":0.2745777245},
{"learn":[1.031897797],"iteration":940,"passed_time":4.304711275,"remaining_time":0.2699021947},
{"learn":[1.03064005],"iteration":941,"passed_time":4.307865513,"remaining_time":0.2652401271},
{"learn":[1.029340526],"iteration":942,"passed_time":4.31100615,"remaining_time":0.2605804354},
{"learn":[1.027902568],"iteration":943,"passed_time":4.31426147,"remaining_time":0.2559307652},
{"learn":[1.02636397],"iteration":944,"passed_time":4.317309195,"remaining_time":0.2512719638},
{"learn":[1.024936623],"iteration":945,"passed_time":4.320176887,"remaining_time":0.2466062916},
{"learn":[1.023504374],"iteration":946,"passed_time":4.323105893,"remaining_time":0.2419478483},
{"learn":[1.022008647],"iteration":947,"passed_time":4.326378745,"remaining_time":0.2373119143},
{"learn":[1.020000764],"iteration":948,"passed_time":4.329242626,"remaining_time":0.2326568745},
{"learn":[1.019067265],"iteration":949,"passed_time":4.332371528,"remaining_time":0.2280195541},
{"learn":[1.016699047],"iteration":950,"passed_time":4.335473125,"remaining_time":0.2233839991},
{"learn":[1.015692153],"iteration":951,"passed_time":4.338764281,"remaining_time":0.2187612243},
{"learn":[1.014899451],"iteration":952,"passed_time":4.342585102,"remaining_time":0.214167366},
{"learn":[1.013572588],"iteration":953,"passed_time":4.345713681,"remaining_time":0.2095417498},
{"learn":[1.012456105],"iteration":954,"passed_time":4.348763768,"remaining_time":0.2049155702},
{"learn":[1.011421756],"iteration":955,"passed_time":4.351805055,"remaining_time":0.2002922829},
{"learn":[1.01001596],"iteration":956,"passed_time":4.354628274,"remaining_time":0.1956625035},
{"learn":[1.009065937],"iteration":957,"passed_time":4.358268794,"remaining_time":0.1910723271},
{"learn":[1.008119081],"iteration":958,"passed_time":4.361104523,"remaining_time":0.1864497241},
{"learn":[1.007015073],"iteration":959,"passed_time":4.363789122,"remaining_time":0.1818245467},
{"learn":[1.005461694],"iteration":960,"passed_time":4.366549171,"remaining_time":0.17720647},
{"learn":[1.00368033],"iteration":961,"passed_time":4.369313953,"remaining_time":0.172592443},
{"learn":[1.002503506],"iteration":962,"passed_time":4.372689968,"remaining_time":0.1680057412},
{"learn":[1.001152168],"iteration":963,"passed_time":4.375607808,"remaining_time":0.163404441},
{"learn":[1.000332289],"iteration":964,"passed_time":4.378392644,"remaining_time":0.1588018057},
{"learn":[0.9988744364],"iteration":965,"passed_time":4.381085344,"remaining_time":0.1541996912},
{"learn":[0.9975432903],"iteration":966,"passed_time":4.384041857,"remaining_time":0.1496105287},
{"learn":[0.9969262414],"iteration":967,"passed_time":4.387018037,"remaining_time":0.1450253896},
{"learn":[0.9957461235],"iteration":968,"passed_time":4.3902508,"remaining_time":0.14045178},
{"learn":[0.9946206048],"iteration":969,"passed_time":4.392650091,"remaining_time":0.1358551575},
{"learn":[0.9931478028],"iteration":970,"passed_time":4.394920091,"remaining_time":0.1312591994},
{"learn":[0.9916202989],"iteration":971,"passed_time":4.397183753,"remaining_time":0.1266678447},
{"learn":[0.990390001],"iteration":972,"passed_time":4.399849187,"remaining_time":0.1220924235},
{"learn":[0.9883942269],"iteration":973,"passed_time":4.403139559,"remaining_time":0.1175376063},
{"learn":[0.9879066052],"iteration":974,"passed_time":4.406894463,"remaining_time":0.1129972939},
{"learn":[0.987509981],"iteration":975,"passed_time":4.410399907,"remaining_time":0.1084524567},
{"learn":[0.9866043069],"iteration":976,"passed_time":4.412957913,"remaining_time":0.1038874432},
{"learn":[0.985722956],"iteration":977,"passed_time":4.415337411,"remaining_time":0.09932251845},
{"learn":[0.9848142112],"iteration":978,"passed_time":4.417931013,"remaining_time":0.09476665095},
{"learn":[0.9837958145],"iteration":979,"passed_time":4.421501192,"remaining_time":0.09023471821},
{"learn":[0.9819251116],"iteration":980,"passed_time":4.424732884,"remaining_time":0.08569819041},
{"learn":[0.9805537546],"iteration":981,"passed_time":4.427844324,"remaining_time":0.08116211591},
{"learn":[0.9792378751],"iteration":982,"passed_time":4.430697742,"remaining_time":0.07662447774},
{"learn":[0.9782999915],"iteration":983,"passed_time":4.433077409,"remaining_time":0.07208255949},
{"learn":[0.9771485491],"iteration":984,"passed_time":4.437096466,"remaining_time":0.06756999695},
{"learn":[0.9758737604],"iteration":985,"passed_time":4.439969752,"remaining_time":0.06304216686},
{"learn":[0.9736985709],"iteration":986,"passed_time":4.442760479,"remaining_time":0.05851660206},
{"learn":[0.9719528082],"iteration":987,"passed_time":4.445434531,"remaining_time":0.05399313196},
{"learn":[0.9702362507],"iteration":988,"passed_time":4.447887298,"remaining_time":0.04947094062},
{"learn":[0.9698728528],"iteration":989,"passed_time":4.451029193,"remaining_time":0.04495989083},
{"learn":[0.9682248937],"iteration":990,"passed_time":4.453691689,"remaining_time":0.04044725046},
{"learn":[0.9661708091],"iteration":991,"passed_time":4.456096546,"remaining_time":0.03593626247},
{"learn":[0.9649783123],"iteration":992,"passed_time":4.458414785,"remaining_time":0.03142890583},
{"learn":[0.963184129],"iteration":993,"passed_time":4.46075652,"remaining_time":0.02692609569},
{"learn":[0.9628292568],"iteration":994,"passed_time":4.463221734,"remaining_time":0.02242824992},
{"learn":[0.9624296088],"iteration":995,"passed_time":4.466043623,"remaining_time":0.01793591817},
{"learn":[0.9610803667],"iteration":996,"passed_time":4.468788477,"remaining_time":0.01344670555},
{"learn":[0.9607075513],"iteration":997,"passed_time":4.471052902,"remaining_time":0.008960025856},
{"learn":[0.9595607321],"iteration":998,"passed_time":4.47334959,"remaining_time":0.004477827418},
{"learn":[0.9584116131],"iteration":999,"passed_time":4.475613816,"remaining_time":0}
]}